.class public Main
.super java/lang/Object
		 
		
.method public static main([Ljava/lang/String;)V
.limit stack 128
.limit locals 128
		new Main
		invokespecial Main/<init>()V
		return
.end method
		 
.method public <init>()V
.limit stack 128
.limit locals 128
		aload 0
		invokespecial java/lang/Object/<init>()V
		aconst_null
		astore 1
		new java/util/ArrayList
		dup
		invokespecial java/util/ArrayList/<init>()V
		astore 6
		aload 6
		ldc ""
		invokevirtual java/util/ArrayList/add(Ljava/lang/Object;)Z
		pop
		aload 6
		ldc ""
		invokevirtual java/util/ArrayList/add(Ljava/lang/Object;)Z
		pop
		aload 6
		ldc ""
		invokevirtual java/util/ArrayList/add(Ljava/lang/Object;)Z
		pop
		aload 6
		ldc ""
		invokevirtual java/util/ArrayList/add(Ljava/lang/Object;)Z
		pop
		aload 6
		ldc ""
		invokevirtual java/util/ArrayList/add(Ljava/lang/Object;)Z
		pop
		aload 6
		ldc ""
		invokevirtual java/util/ArrayList/add(Ljava/lang/Object;)Z
		pop
		aload 6
		ldc ""
		invokevirtual java/util/ArrayList/add(Ljava/lang/Object;)Z
		pop
		aload 6
		ldc ""
		invokevirtual java/util/ArrayList/add(Ljava/lang/Object;)Z
		pop
		aload 6
		ldc ""
		invokevirtual java/util/ArrayList/add(Ljava/lang/Object;)Z
		pop
		aload 6
		ldc ""
		invokevirtual java/util/ArrayList/add(Ljava/lang/Object;)Z
		pop
		aload 6
		ldc ""
		invokevirtual java/util/ArrayList/add(Ljava/lang/Object;)Z
		pop
		aload 6
		ldc ""
		invokevirtual java/util/ArrayList/add(Ljava/lang/Object;)Z
		pop
		aload 6
		ldc ""
		invokevirtual java/util/ArrayList/add(Ljava/lang/Object;)Z
		pop
		aload 6
		ldc ""
		invokevirtual java/util/ArrayList/add(Ljava/lang/Object;)Z
		pop
		aload 6
		ldc ""
		invokevirtual java/util/ArrayList/add(Ljava/lang/Object;)Z
		pop
		aload 6
		ldc ""
		invokevirtual java/util/ArrayList/add(Ljava/lang/Object;)Z
		pop
		aload 6
		ldc ""
		invokevirtual java/util/ArrayList/add(Ljava/lang/Object;)Z
		pop
		aload 6
		ldc ""
		invokevirtual java/util/ArrayList/add(Ljava/lang/Object;)Z
		pop
		aload 6
		ldc ""
		invokevirtual java/util/ArrayList/add(Ljava/lang/Object;)Z
		pop
		aload 6
		ldc ""
		invokevirtual java/util/ArrayList/add(Ljava/lang/Object;)Z
		pop
		aload 6
		ldc ""
		invokevirtual java/util/ArrayList/add(Ljava/lang/Object;)Z
		pop
		aload 6
		ldc ""
		invokevirtual java/util/ArrayList/add(Ljava/lang/Object;)Z
		pop
		aload 6
		ldc ""
		invokevirtual java/util/ArrayList/add(Ljava/lang/Object;)Z
		pop
		aload 6
		ldc ""
		invokevirtual java/util/ArrayList/add(Ljava/lang/Object;)Z
		pop
		aload 6
		ldc ""
		invokevirtual java/util/ArrayList/add(Ljava/lang/Object;)Z
		pop
		aload 6
		ldc ""
		invokevirtual java/util/ArrayList/add(Ljava/lang/Object;)Z
		pop
		aload 6
		ldc ""
		invokevirtual java/util/ArrayList/add(Ljava/lang/Object;)Z
		pop
		aload 6
		ldc ""
		invokevirtual java/util/ArrayList/add(Ljava/lang/Object;)Z
		pop
		aload 6
		ldc ""
		invokevirtual java/util/ArrayList/add(Ljava/lang/Object;)Z
		pop
		aload 6
		ldc ""
		invokevirtual java/util/ArrayList/add(Ljava/lang/Object;)Z
		pop
		aload 6
		ldc ""
		invokevirtual java/util/ArrayList/add(Ljava/lang/Object;)Z
		pop
		aload 6
		ldc ""
		invokevirtual java/util/ArrayList/add(Ljava/lang/Object;)Z
		pop
		aload 6
		ldc ""
		invokevirtual java/util/ArrayList/add(Ljava/lang/Object;)Z
		pop
		aload 6
		ldc ""
		invokevirtual java/util/ArrayList/add(Ljava/lang/Object;)Z
		pop
		aload 6
		ldc ""
		invokevirtual java/util/ArrayList/add(Ljava/lang/Object;)Z
		pop
		aload 6
		ldc ""
		invokevirtual java/util/ArrayList/add(Ljava/lang/Object;)Z
		pop
		aload 6
		ldc ""
		invokevirtual java/util/ArrayList/add(Ljava/lang/Object;)Z
		pop
		aload 6
		ldc ""
		invokevirtual java/util/ArrayList/add(Ljava/lang/Object;)Z
		pop
		aload 6
		ldc ""
		invokevirtual java/util/ArrayList/add(Ljava/lang/Object;)Z
		pop
		aload 6
		ldc ""
		invokevirtual java/util/ArrayList/add(Ljava/lang/Object;)Z
		pop
		aload 6
		ldc ""
		invokevirtual java/util/ArrayList/add(Ljava/lang/Object;)Z
		pop
		aload 6
		ldc ""
		invokevirtual java/util/ArrayList/add(Ljava/lang/Object;)Z
		pop
		aload 6
		ldc ""
		invokevirtual java/util/ArrayList/add(Ljava/lang/Object;)Z
		pop
		aload 6
		ldc ""
		invokevirtual java/util/ArrayList/add(Ljava/lang/Object;)Z
		pop
		aload 6
		ldc ""
		invokevirtual java/util/ArrayList/add(Ljava/lang/Object;)Z
		pop
		aload 6
		ldc ""
		invokevirtual java/util/ArrayList/add(Ljava/lang/Object;)Z
		pop
		aload 6
		ldc ""
		invokevirtual java/util/ArrayList/add(Ljava/lang/Object;)Z
		pop
		aload 6
		ldc ""
		invokevirtual java/util/ArrayList/add(Ljava/lang/Object;)Z
		pop
		aload 6
		ldc ""
		invokevirtual java/util/ArrayList/add(Ljava/lang/Object;)Z
		pop
		aload 6
		ldc ""
		invokevirtual java/util/ArrayList/add(Ljava/lang/Object;)Z
		pop
		aload 6
		ldc ""
		invokevirtual java/util/ArrayList/add(Ljava/lang/Object;)Z
		pop
		aload 6
		ldc ""
		invokevirtual java/util/ArrayList/add(Ljava/lang/Object;)Z
		pop
		aload 6
		ldc ""
		invokevirtual java/util/ArrayList/add(Ljava/lang/Object;)Z
		pop
		aload 6
		ldc ""
		invokevirtual java/util/ArrayList/add(Ljava/lang/Object;)Z
		pop
		aload 6
		ldc ""
		invokevirtual java/util/ArrayList/add(Ljava/lang/Object;)Z
		pop
		aload 6
		ldc ""
		invokevirtual java/util/ArrayList/add(Ljava/lang/Object;)Z
		pop
		aload 6
		ldc ""
		invokevirtual java/util/ArrayList/add(Ljava/lang/Object;)Z
		pop
		aload 6
		ldc ""
		invokevirtual java/util/ArrayList/add(Ljava/lang/Object;)Z
		pop
		aload 6
		ldc ""
		invokevirtual java/util/ArrayList/add(Ljava/lang/Object;)Z
		pop
		aload 6
		ldc ""
		invokevirtual java/util/ArrayList/add(Ljava/lang/Object;)Z
		pop
		aload 6
		ldc ""
		invokevirtual java/util/ArrayList/add(Ljava/lang/Object;)Z
		pop
		aload 6
		ldc ""
		invokevirtual java/util/ArrayList/add(Ljava/lang/Object;)Z
		pop
		aload 6
		ldc ""
		invokevirtual java/util/ArrayList/add(Ljava/lang/Object;)Z
		pop
		aload 6
		ldc ""
		invokevirtual java/util/ArrayList/add(Ljava/lang/Object;)Z
		pop
		aload 6
		ldc ""
		invokevirtual java/util/ArrayList/add(Ljava/lang/Object;)Z
		pop
		aload 6
		ldc ""
		invokevirtual java/util/ArrayList/add(Ljava/lang/Object;)Z
		pop
		aload 6
		ldc ""
		invokevirtual java/util/ArrayList/add(Ljava/lang/Object;)Z
		pop
		aload 6
		ldc ""
		invokevirtual java/util/ArrayList/add(Ljava/lang/Object;)Z
		pop
		aload 6
		ldc ""
		invokevirtual java/util/ArrayList/add(Ljava/lang/Object;)Z
		pop
		aload 6
		ldc ""
		invokevirtual java/util/ArrayList/add(Ljava/lang/Object;)Z
		pop
		aload 6
		ldc ""
		invokevirtual java/util/ArrayList/add(Ljava/lang/Object;)Z
		pop
		aload 6
		ldc ""
		invokevirtual java/util/ArrayList/add(Ljava/lang/Object;)Z
		pop
		aload 6
		ldc ""
		invokevirtual java/util/ArrayList/add(Ljava/lang/Object;)Z
		pop
		aload 6
		ldc ""
		invokevirtual java/util/ArrayList/add(Ljava/lang/Object;)Z
		pop
		aload 6
		ldc ""
		invokevirtual java/util/ArrayList/add(Ljava/lang/Object;)Z
		pop
		aload 6
		ldc ""
		invokevirtual java/util/ArrayList/add(Ljava/lang/Object;)Z
		pop
		aload 6
		ldc ""
		invokevirtual java/util/ArrayList/add(Ljava/lang/Object;)Z
		pop
		aload 6
		ldc ""
		invokevirtual java/util/ArrayList/add(Ljava/lang/Object;)Z
		pop
		aload 6
		ldc ""
		invokevirtual java/util/ArrayList/add(Ljava/lang/Object;)Z
		pop
		aload 6
		ldc ""
		invokevirtual java/util/ArrayList/add(Ljava/lang/Object;)Z
		pop
		aload 6
		ldc ""
		invokevirtual java/util/ArrayList/add(Ljava/lang/Object;)Z
		pop
		aload 6
		ldc ""
		invokevirtual java/util/ArrayList/add(Ljava/lang/Object;)Z
		pop
		aload 6
		ldc ""
		invokevirtual java/util/ArrayList/add(Ljava/lang/Object;)Z
		pop
		aload 6
		ldc ""
		invokevirtual java/util/ArrayList/add(Ljava/lang/Object;)Z
		pop
		aload 6
		ldc ""
		invokevirtual java/util/ArrayList/add(Ljava/lang/Object;)Z
		pop
		aload 6
		ldc ""
		invokevirtual java/util/ArrayList/add(Ljava/lang/Object;)Z
		pop
		aload 6
		ldc ""
		invokevirtual java/util/ArrayList/add(Ljava/lang/Object;)Z
		pop
		aload 6
		ldc ""
		invokevirtual java/util/ArrayList/add(Ljava/lang/Object;)Z
		pop
		aload 6
		ldc ""
		invokevirtual java/util/ArrayList/add(Ljava/lang/Object;)Z
		pop
		aload 6
		ldc ""
		invokevirtual java/util/ArrayList/add(Ljava/lang/Object;)Z
		pop
		aload 6
		ldc ""
		invokevirtual java/util/ArrayList/add(Ljava/lang/Object;)Z
		pop
		aload 6
		ldc ""
		invokevirtual java/util/ArrayList/add(Ljava/lang/Object;)Z
		pop
		aload 6
		ldc ""
		invokevirtual java/util/ArrayList/add(Ljava/lang/Object;)Z
		pop
		aload 6
		ldc ""
		invokevirtual java/util/ArrayList/add(Ljava/lang/Object;)Z
		pop
		aload 6
		ldc ""
		invokevirtual java/util/ArrayList/add(Ljava/lang/Object;)Z
		pop
		aload 6
		ldc ""
		invokevirtual java/util/ArrayList/add(Ljava/lang/Object;)Z
		pop
		aload 6
		ldc ""
		invokevirtual java/util/ArrayList/add(Ljava/lang/Object;)Z
		pop
		aload 6
		ldc ""
		invokevirtual java/util/ArrayList/add(Ljava/lang/Object;)Z
		pop
		aload 6
		ldc ""
		invokevirtual java/util/ArrayList/add(Ljava/lang/Object;)Z
		pop
		aload 6
		ldc ""
		invokevirtual java/util/ArrayList/add(Ljava/lang/Object;)Z
		pop
		new List
		dup
		aload 6
		invokespecial List/<init>(Ljava/util/ArrayList;)V
		astore 2
		ldc 0
		invokestatic java/lang/Integer/valueOf(I)Ljava/lang/Integer;
		astore 3
		ldc ""
		astore 4
		ldc ""
		astore 5
		ldc "hi"
		dup
		astore 4
		pop
		ldc "hi"
		dup
		astore 5
		pop
		aload 4
		aload 5
		if_acmpne Label_22
		ldc 1
		goto Label_23
		Label_22:
		ldc 0
		Label_23:
		ifeq Label_20
		getstatic java/lang/System/out Ljava/io/PrintStream;
		ldc "asdkjasdkjanskjdsakdnkanjdskankjdnakjsndjas"
		invokevirtual java/io/PrintStream/print(Ljava/lang/String;)V
		goto Label_21
	Label_20:
	Label_21:
		new WordProcessor
		dup
		invokespecial WordProcessor/<init>()V
		dup
		astore 1
		pop
		ldc 0
		dup
		invokestatic java/lang/Integer/valueOf(I)Ljava/lang/Integer;
		astore 3
		pop
	Label_24:
		aload 3
		invokevirtual java/lang/Integer/intValue()I
		ldc 50
		if_icmpge Label_27
		ldc 1
		goto Label_28
		Label_27:
		ldc 0
		Label_28:
		ifeq Label_25
		aload 2
		aload 3
		invokevirtual java/lang/Integer/intValue()I
		ldc "amir"
		dup_x2
		invokevirtual List/setElement(ILjava/lang/Object;)V
		pop
	Label_26:
		aload 3
		invokevirtual java/lang/Integer/intValue()I
		ldc 1
		iadd
		dup
		invokestatic java/lang/Integer/valueOf(I)Ljava/lang/Integer;
		astore 3
		pop
		goto Label_24
	Label_25:
		ldc 50
		dup
		invokestatic java/lang/Integer/valueOf(I)Ljava/lang/Integer;
		astore 3
		pop
	Label_29:
		aload 3
		invokevirtual java/lang/Integer/intValue()I
		ldc 100
		if_icmpge Label_32
		ldc 1
		goto Label_33
		Label_32:
		ldc 0
		Label_33:
		ifeq Label_30
		aload 2
		aload 3
		invokevirtual java/lang/Integer/intValue()I
		ldc "ali"
		dup_x2
		invokevirtual List/setElement(ILjava/lang/Object;)V
		pop
	Label_31:
		aload 3
		invokevirtual java/lang/Integer/intValue()I
		ldc 1
		iadd
		dup
		invokestatic java/lang/Integer/valueOf(I)Ljava/lang/Integer;
		astore 3
		pop
		goto Label_29
	Label_30:
		new java/util/ArrayList
		dup
		invokespecial java/util/ArrayList/<init>()V
		astore 6
		aload 6
		aload 2
		invokevirtual java/util/ArrayList/add(Ljava/lang/Object;)Z
		pop
		new Fptr
		dup
		aload 1
		ldc "wordProcess"
		invokespecial Fptr/<init>(Ljava/lang/Object;Ljava/lang/String;)V
		aload 6
		invokevirtual Fptr/invoke(Ljava/util/ArrayList;)Ljava/lang/Object;
		pop
		getstatic java/lang/System/out Ljava/io/PrintStream;
		ldc "\n"
		invokevirtual java/io/PrintStream/print(Ljava/lang/String;)V
		getstatic java/lang/System/out Ljava/io/PrintStream;
		new java/util/ArrayList
		dup
		invokespecial java/util/ArrayList/<init>()V
		astore 6
		aload 6
		ldc 1
		invokestatic java/lang/Integer/valueOf(I)Ljava/lang/Integer;
		invokevirtual java/util/ArrayList/add(Ljava/lang/Object;)Z
		pop
		new Fptr
		dup
		aload 0
		ldc "foo"
		invokespecial Fptr/<init>(Ljava/lang/Object;Ljava/lang/String;)V
		aload 6
		invokevirtual Fptr/invoke(Ljava/util/ArrayList;)Ljava/lang/Object;
		
		checkcast java/lang/Integer
		invokevirtual java/lang/Integer/intValue()I
		invokevirtual java/io/PrintStream/print(I)V
		return
.end method
		 
.method public foo(Ljava/lang/Integer;)Ljava/lang/Integer;
.limit stack 128
.limit locals 128
		aload 1
		invokevirtual java/lang/Integer/intValue()I
		ldc 1
		if_icmpne Label_36
		ldc 1
		goto Label_37
		Label_36:
		ldc 0
		Label_37:
		ifeq Label_34
		ldc 2
		invokestatic java/lang/Integer/valueOf(I)Ljava/lang/Integer;
		areturn
	Label_34:
		ldc 3
		invokestatic java/lang/Integer/valueOf(I)Ljava/lang/Integer;
		areturn
	Label_35:
.end method
		 
