.class public Main
.super java/lang/Object
		 
.field rrr LFptr;
		
.method public static main([Ljava/lang/String;)V
.limit stack 128
.limit locals 128
		new Main
		invokespecial Main/<init>()V
		return
.end method
		 
.method public <init>()V
.limit stack 128
.limit locals 128
		aload 0
		invokespecial java/lang/Object/<init>()V
		aload 0
		aconst_null
		putfield Main/rrr LFptr;
		aconst_null
		astore 1
		new java/util/ArrayList
		dup
		invokespecial java/util/ArrayList/<init>()V
		astore 4
		aload 4
		ldc ""
		invokevirtual java/util/ArrayList/add(Ljava/lang/Object;)Z
		pop
		aload 4
		ldc ""
		invokevirtual java/util/ArrayList/add(Ljava/lang/Object;)Z
		pop
		aload 4
		ldc ""
		invokevirtual java/util/ArrayList/add(Ljava/lang/Object;)Z
		pop
		aload 4
		ldc ""
		invokevirtual java/util/ArrayList/add(Ljava/lang/Object;)Z
		pop
		aload 4
		ldc ""
		invokevirtual java/util/ArrayList/add(Ljava/lang/Object;)Z
		pop
		aload 4
		ldc ""
		invokevirtual java/util/ArrayList/add(Ljava/lang/Object;)Z
		pop
		aload 4
		ldc ""
		invokevirtual java/util/ArrayList/add(Ljava/lang/Object;)Z
		pop
		aload 4
		ldc ""
		invokevirtual java/util/ArrayList/add(Ljava/lang/Object;)Z
		pop
		aload 4
		ldc ""
		invokevirtual java/util/ArrayList/add(Ljava/lang/Object;)Z
		pop
		aload 4
		ldc ""
		invokevirtual java/util/ArrayList/add(Ljava/lang/Object;)Z
		pop
		aload 4
		ldc ""
		invokevirtual java/util/ArrayList/add(Ljava/lang/Object;)Z
		pop
		aload 4
		ldc ""
		invokevirtual java/util/ArrayList/add(Ljava/lang/Object;)Z
		pop
		aload 4
		ldc ""
		invokevirtual java/util/ArrayList/add(Ljava/lang/Object;)Z
		pop
		aload 4
		ldc ""
		invokevirtual java/util/ArrayList/add(Ljava/lang/Object;)Z
		pop
		aload 4
		ldc ""
		invokevirtual java/util/ArrayList/add(Ljava/lang/Object;)Z
		pop
		aload 4
		ldc ""
		invokevirtual java/util/ArrayList/add(Ljava/lang/Object;)Z
		pop
		aload 4
		ldc ""
		invokevirtual java/util/ArrayList/add(Ljava/lang/Object;)Z
		pop
		aload 4
		ldc ""
		invokevirtual java/util/ArrayList/add(Ljava/lang/Object;)Z
		pop
		aload 4
		ldc ""
		invokevirtual java/util/ArrayList/add(Ljava/lang/Object;)Z
		pop
		aload 4
		ldc ""
		invokevirtual java/util/ArrayList/add(Ljava/lang/Object;)Z
		pop
		aload 4
		ldc ""
		invokevirtual java/util/ArrayList/add(Ljava/lang/Object;)Z
		pop
		aload 4
		ldc ""
		invokevirtual java/util/ArrayList/add(Ljava/lang/Object;)Z
		pop
		aload 4
		ldc ""
		invokevirtual java/util/ArrayList/add(Ljava/lang/Object;)Z
		pop
		aload 4
		ldc ""
		invokevirtual java/util/ArrayList/add(Ljava/lang/Object;)Z
		pop
		aload 4
		ldc ""
		invokevirtual java/util/ArrayList/add(Ljava/lang/Object;)Z
		pop
		aload 4
		ldc ""
		invokevirtual java/util/ArrayList/add(Ljava/lang/Object;)Z
		pop
		aload 4
		ldc ""
		invokevirtual java/util/ArrayList/add(Ljava/lang/Object;)Z
		pop
		aload 4
		ldc ""
		invokevirtual java/util/ArrayList/add(Ljava/lang/Object;)Z
		pop
		aload 4
		ldc ""
		invokevirtual java/util/ArrayList/add(Ljava/lang/Object;)Z
		pop
		aload 4
		ldc ""
		invokevirtual java/util/ArrayList/add(Ljava/lang/Object;)Z
		pop
		aload 4
		ldc ""
		invokevirtual java/util/ArrayList/add(Ljava/lang/Object;)Z
		pop
		aload 4
		ldc ""
		invokevirtual java/util/ArrayList/add(Ljava/lang/Object;)Z
		pop
		aload 4
		ldc ""
		invokevirtual java/util/ArrayList/add(Ljava/lang/Object;)Z
		pop
		aload 4
		ldc ""
		invokevirtual java/util/ArrayList/add(Ljava/lang/Object;)Z
		pop
		aload 4
		ldc ""
		invokevirtual java/util/ArrayList/add(Ljava/lang/Object;)Z
		pop
		aload 4
		ldc ""
		invokevirtual java/util/ArrayList/add(Ljava/lang/Object;)Z
		pop
		aload 4
		ldc ""
		invokevirtual java/util/ArrayList/add(Ljava/lang/Object;)Z
		pop
		aload 4
		ldc ""
		invokevirtual java/util/ArrayList/add(Ljava/lang/Object;)Z
		pop
		aload 4
		ldc ""
		invokevirtual java/util/ArrayList/add(Ljava/lang/Object;)Z
		pop
		aload 4
		ldc ""
		invokevirtual java/util/ArrayList/add(Ljava/lang/Object;)Z
		pop
		aload 4
		ldc ""
		invokevirtual java/util/ArrayList/add(Ljava/lang/Object;)Z
		pop
		aload 4
		ldc ""
		invokevirtual java/util/ArrayList/add(Ljava/lang/Object;)Z
		pop
		aload 4
		ldc ""
		invokevirtual java/util/ArrayList/add(Ljava/lang/Object;)Z
		pop
		aload 4
		ldc ""
		invokevirtual java/util/ArrayList/add(Ljava/lang/Object;)Z
		pop
		aload 4
		ldc ""
		invokevirtual java/util/ArrayList/add(Ljava/lang/Object;)Z
		pop
		aload 4
		ldc ""
		invokevirtual java/util/ArrayList/add(Ljava/lang/Object;)Z
		pop
		aload 4
		ldc ""
		invokevirtual java/util/ArrayList/add(Ljava/lang/Object;)Z
		pop
		aload 4
		ldc ""
		invokevirtual java/util/ArrayList/add(Ljava/lang/Object;)Z
		pop
		aload 4
		ldc ""
		invokevirtual java/util/ArrayList/add(Ljava/lang/Object;)Z
		pop
		aload 4
		ldc ""
		invokevirtual java/util/ArrayList/add(Ljava/lang/Object;)Z
		pop
		aload 4
		ldc ""
		invokevirtual java/util/ArrayList/add(Ljava/lang/Object;)Z
		pop
		aload 4
		ldc ""
		invokevirtual java/util/ArrayList/add(Ljava/lang/Object;)Z
		pop
		aload 4
		ldc ""
		invokevirtual java/util/ArrayList/add(Ljava/lang/Object;)Z
		pop
		aload 4
		ldc ""
		invokevirtual java/util/ArrayList/add(Ljava/lang/Object;)Z
		pop
		aload 4
		ldc ""
		invokevirtual java/util/ArrayList/add(Ljava/lang/Object;)Z
		pop
		aload 4
		ldc ""
		invokevirtual java/util/ArrayList/add(Ljava/lang/Object;)Z
		pop
		aload 4
		ldc ""
		invokevirtual java/util/ArrayList/add(Ljava/lang/Object;)Z
		pop
		aload 4
		ldc ""
		invokevirtual java/util/ArrayList/add(Ljava/lang/Object;)Z
		pop
		aload 4
		ldc ""
		invokevirtual java/util/ArrayList/add(Ljava/lang/Object;)Z
		pop
		aload 4
		ldc ""
		invokevirtual java/util/ArrayList/add(Ljava/lang/Object;)Z
		pop
		aload 4
		ldc ""
		invokevirtual java/util/ArrayList/add(Ljava/lang/Object;)Z
		pop
		aload 4
		ldc ""
		invokevirtual java/util/ArrayList/add(Ljava/lang/Object;)Z
		pop
		aload 4
		ldc ""
		invokevirtual java/util/ArrayList/add(Ljava/lang/Object;)Z
		pop
		aload 4
		ldc ""
		invokevirtual java/util/ArrayList/add(Ljava/lang/Object;)Z
		pop
		aload 4
		ldc ""
		invokevirtual java/util/ArrayList/add(Ljava/lang/Object;)Z
		pop
		aload 4
		ldc ""
		invokevirtual java/util/ArrayList/add(Ljava/lang/Object;)Z
		pop
		aload 4
		ldc ""
		invokevirtual java/util/ArrayList/add(Ljava/lang/Object;)Z
		pop
		aload 4
		ldc ""
		invokevirtual java/util/ArrayList/add(Ljava/lang/Object;)Z
		pop
		aload 4
		ldc ""
		invokevirtual java/util/ArrayList/add(Ljava/lang/Object;)Z
		pop
		aload 4
		ldc ""
		invokevirtual java/util/ArrayList/add(Ljava/lang/Object;)Z
		pop
		aload 4
		ldc ""
		invokevirtual java/util/ArrayList/add(Ljava/lang/Object;)Z
		pop
		aload 4
		ldc ""
		invokevirtual java/util/ArrayList/add(Ljava/lang/Object;)Z
		pop
		aload 4
		ldc ""
		invokevirtual java/util/ArrayList/add(Ljava/lang/Object;)Z
		pop
		aload 4
		ldc ""
		invokevirtual java/util/ArrayList/add(Ljava/lang/Object;)Z
		pop
		aload 4
		ldc ""
		invokevirtual java/util/ArrayList/add(Ljava/lang/Object;)Z
		pop
		aload 4
		ldc ""
		invokevirtual java/util/ArrayList/add(Ljava/lang/Object;)Z
		pop
		aload 4
		ldc ""
		invokevirtual java/util/ArrayList/add(Ljava/lang/Object;)Z
		pop
		aload 4
		ldc ""
		invokevirtual java/util/ArrayList/add(Ljava/lang/Object;)Z
		pop
		aload 4
		ldc ""
		invokevirtual java/util/ArrayList/add(Ljava/lang/Object;)Z
		pop
		aload 4
		ldc ""
		invokevirtual java/util/ArrayList/add(Ljava/lang/Object;)Z
		pop
		aload 4
		ldc ""
		invokevirtual java/util/ArrayList/add(Ljava/lang/Object;)Z
		pop
		aload 4
		ldc ""
		invokevirtual java/util/ArrayList/add(Ljava/lang/Object;)Z
		pop
		aload 4
		ldc ""
		invokevirtual java/util/ArrayList/add(Ljava/lang/Object;)Z
		pop
		aload 4
		ldc ""
		invokevirtual java/util/ArrayList/add(Ljava/lang/Object;)Z
		pop
		aload 4
		ldc ""
		invokevirtual java/util/ArrayList/add(Ljava/lang/Object;)Z
		pop
		aload 4
		ldc ""
		invokevirtual java/util/ArrayList/add(Ljava/lang/Object;)Z
		pop
		aload 4
		ldc ""
		invokevirtual java/util/ArrayList/add(Ljava/lang/Object;)Z
		pop
		aload 4
		ldc ""
		invokevirtual java/util/ArrayList/add(Ljava/lang/Object;)Z
		pop
		aload 4
		ldc ""
		invokevirtual java/util/ArrayList/add(Ljava/lang/Object;)Z
		pop
		aload 4
		ldc ""
		invokevirtual java/util/ArrayList/add(Ljava/lang/Object;)Z
		pop
		aload 4
		ldc ""
		invokevirtual java/util/ArrayList/add(Ljava/lang/Object;)Z
		pop
		aload 4
		ldc ""
		invokevirtual java/util/ArrayList/add(Ljava/lang/Object;)Z
		pop
		aload 4
		ldc ""
		invokevirtual java/util/ArrayList/add(Ljava/lang/Object;)Z
		pop
		aload 4
		ldc ""
		invokevirtual java/util/ArrayList/add(Ljava/lang/Object;)Z
		pop
		aload 4
		ldc ""
		invokevirtual java/util/ArrayList/add(Ljava/lang/Object;)Z
		pop
		aload 4
		ldc ""
		invokevirtual java/util/ArrayList/add(Ljava/lang/Object;)Z
		pop
		aload 4
		ldc ""
		invokevirtual java/util/ArrayList/add(Ljava/lang/Object;)Z
		pop
		aload 4
		ldc ""
		invokevirtual java/util/ArrayList/add(Ljava/lang/Object;)Z
		pop
		aload 4
		ldc ""
		invokevirtual java/util/ArrayList/add(Ljava/lang/Object;)Z
		pop
		aload 4
		ldc ""
		invokevirtual java/util/ArrayList/add(Ljava/lang/Object;)Z
		pop
		new List
		dup
		aload 4
		invokespecial List/<init>(Ljava/util/ArrayList;)V
		astore 2
		ldc 0
		invokestatic java/lang/Integer/valueOf(I)Ljava/lang/Integer;
		astore 3
		new WordProcessor
		dup
		invokespecial WordProcessor/<init>()V
		dup
		astore 1
		pop
		ldc 0
		dup
		invokestatic java/lang/Integer/valueOf(I)Ljava/lang/Integer;
		astore 3
		pop
	Label_20:
		aload 3
		invokevirtual java/lang/Integer/intValue()I
		ldc 50
		if_icmpge Label_23
		ldc 1
		goto Label_24
		Label_23:
		ldc 0
		Label_24:
		ifeq Label_21
		aload 2
		aload 3
		invokevirtual java/lang/Integer/intValue()I
		ldc "amir"
		dup_x2
		invokevirtual List/setElement(ILjava/lang/Object;)V
		pop
	Label_22:
		aload 3
		invokevirtual java/lang/Integer/intValue()I
		ldc 1
		iadd
		dup
		invokestatic java/lang/Integer/valueOf(I)Ljava/lang/Integer;
		astore 3
		pop
		goto Label_20
	Label_21:
		ldc 50
		dup
		invokestatic java/lang/Integer/valueOf(I)Ljava/lang/Integer;
		astore 3
		pop
	Label_25:
		aload 3
		invokevirtual java/lang/Integer/intValue()I
		ldc 100
		if_icmpge Label_28
		ldc 1
		goto Label_29
		Label_28:
		ldc 0
		Label_29:
		ifeq Label_26
		aload 2
		aload 3
		invokevirtual java/lang/Integer/intValue()I
		ldc "ali"
		dup_x2
		invokevirtual List/setElement(ILjava/lang/Object;)V
		pop
	Label_27:
		aload 3
		invokevirtual java/lang/Integer/intValue()I
		ldc 1
		iadd
		dup
		invokestatic java/lang/Integer/valueOf(I)Ljava/lang/Integer;
		astore 3
		pop
		goto Label_25
	Label_26:
		new java/util/ArrayList
		dup
		invokespecial java/util/ArrayList/<init>()V
		astore 4
		aload 4
		aload 2
		invokevirtual java/util/ArrayList/add(Ljava/lang/Object;)Z
		pop
		new Fptr
		dup
		aload 1
		ldc "wordProcess"
		invokespecial Fptr/<init>(Ljava/lang/Object;Ljava/lang/String;)V
		aload 4
		invokevirtual Fptr/invoke(Ljava/util/ArrayList;)Ljava/lang/Object;
		pop
		return
.end method
		 
