.class public WordProcessor
.super java/lang/Object
		 
		
.method public <init>()V
.limit stack 128
.limit locals 128
		aload 0
		invokespecial java/lang/Object/<init>()V
		return
.end method
		 
.method public map(LList;)LList;
.limit stack 128
.limit locals 128
		ldc ""
		astore 2
		ldc 0
		invokestatic java/lang/Integer/valueOf(I)Ljava/lang/Integer;
		astore 3
		ldc 0
		invokestatic java/lang/Boolean/valueOf(Z)Ljava/lang/Boolean;
		astore 4
		new java/util/ArrayList
		dup
		invokespecial java/util/ArrayList/<init>()V
		astore 8
		aload 8
		new java/util/ArrayList
		dup
		invokespecial java/util/ArrayList/<init>()V
		astore 9
		aload 9
		ldc ""
		invokevirtual java/util/ArrayList/add(Ljava/lang/Object;)Z
		pop
		aload 9
		ldc 0
		invokestatic java/lang/Integer/valueOf(I)Ljava/lang/Integer;
		invokevirtual java/util/ArrayList/add(Ljava/lang/Object;)Z
		pop
		new List
		dup
		aload 9
		invokespecial List/<init>(Ljava/util/ArrayList;)V
		invokevirtual java/util/ArrayList/add(Ljava/lang/Object;)Z
		pop
		aload 8
		new java/util/ArrayList
		dup
		invokespecial java/util/ArrayList/<init>()V
		astore 9
		aload 9
		ldc ""
		invokevirtual java/util/ArrayList/add(Ljava/lang/Object;)Z
		pop
		aload 9
		ldc 0
		invokestatic java/lang/Integer/valueOf(I)Ljava/lang/Integer;
		invokevirtual java/util/ArrayList/add(Ljava/lang/Object;)Z
		pop
		new List
		dup
		aload 9
		invokespecial List/<init>(Ljava/util/ArrayList;)V
		invokevirtual java/util/ArrayList/add(Ljava/lang/Object;)Z
		pop
		aload 8
		new java/util/ArrayList
		dup
		invokespecial java/util/ArrayList/<init>()V
		astore 9
		aload 9
		ldc ""
		invokevirtual java/util/ArrayList/add(Ljava/lang/Object;)Z
		pop
		aload 9
		ldc 0
		invokestatic java/lang/Integer/valueOf(I)Ljava/lang/Integer;
		invokevirtual java/util/ArrayList/add(Ljava/lang/Object;)Z
		pop
		new List
		dup
		aload 9
		invokespecial List/<init>(Ljava/util/ArrayList;)V
		invokevirtual java/util/ArrayList/add(Ljava/lang/Object;)Z
		pop
		aload 8
		new java/util/ArrayList
		dup
		invokespecial java/util/ArrayList/<init>()V
		astore 9
		aload 9
		ldc ""
		invokevirtual java/util/ArrayList/add(Ljava/lang/Object;)Z
		pop
		aload 9
		ldc 0
		invokestatic java/lang/Integer/valueOf(I)Ljava/lang/Integer;
		invokevirtual java/util/ArrayList/add(Ljava/lang/Object;)Z
		pop
		new List
		dup
		aload 9
		invokespecial List/<init>(Ljava/util/ArrayList;)V
		invokevirtual java/util/ArrayList/add(Ljava/lang/Object;)Z
		pop
		aload 8
		new java/util/ArrayList
		dup
		invokespecial java/util/ArrayList/<init>()V
		astore 9
		aload 9
		ldc ""
		invokevirtual java/util/ArrayList/add(Ljava/lang/Object;)Z
		pop
		aload 9
		ldc 0
		invokestatic java/lang/Integer/valueOf(I)Ljava/lang/Integer;
		invokevirtual java/util/ArrayList/add(Ljava/lang/Object;)Z
		pop
		new List
		dup
		aload 9
		invokespecial List/<init>(Ljava/util/ArrayList;)V
		invokevirtual java/util/ArrayList/add(Ljava/lang/Object;)Z
		pop
		aload 8
		new java/util/ArrayList
		dup
		invokespecial java/util/ArrayList/<init>()V
		astore 9
		aload 9
		ldc ""
		invokevirtual java/util/ArrayList/add(Ljava/lang/Object;)Z
		pop
		aload 9
		ldc 0
		invokestatic java/lang/Integer/valueOf(I)Ljava/lang/Integer;
		invokevirtual java/util/ArrayList/add(Ljava/lang/Object;)Z
		pop
		new List
		dup
		aload 9
		invokespecial List/<init>(Ljava/util/ArrayList;)V
		invokevirtual java/util/ArrayList/add(Ljava/lang/Object;)Z
		pop
		aload 8
		new java/util/ArrayList
		dup
		invokespecial java/util/ArrayList/<init>()V
		astore 9
		aload 9
		ldc ""
		invokevirtual java/util/ArrayList/add(Ljava/lang/Object;)Z
		pop
		aload 9
		ldc 0
		invokestatic java/lang/Integer/valueOf(I)Ljava/lang/Integer;
		invokevirtual java/util/ArrayList/add(Ljava/lang/Object;)Z
		pop
		new List
		dup
		aload 9
		invokespecial List/<init>(Ljava/util/ArrayList;)V
		invokevirtual java/util/ArrayList/add(Ljava/lang/Object;)Z
		pop
		aload 8
		new java/util/ArrayList
		dup
		invokespecial java/util/ArrayList/<init>()V
		astore 9
		aload 9
		ldc ""
		invokevirtual java/util/ArrayList/add(Ljava/lang/Object;)Z
		pop
		aload 9
		ldc 0
		invokestatic java/lang/Integer/valueOf(I)Ljava/lang/Integer;
		invokevirtual java/util/ArrayList/add(Ljava/lang/Object;)Z
		pop
		new List
		dup
		aload 9
		invokespecial List/<init>(Ljava/util/ArrayList;)V
		invokevirtual java/util/ArrayList/add(Ljava/lang/Object;)Z
		pop
		aload 8
		new java/util/ArrayList
		dup
		invokespecial java/util/ArrayList/<init>()V
		astore 9
		aload 9
		ldc ""
		invokevirtual java/util/ArrayList/add(Ljava/lang/Object;)Z
		pop
		aload 9
		ldc 0
		invokestatic java/lang/Integer/valueOf(I)Ljava/lang/Integer;
		invokevirtual java/util/ArrayList/add(Ljava/lang/Object;)Z
		pop
		new List
		dup
		aload 9
		invokespecial List/<init>(Ljava/util/ArrayList;)V
		invokevirtual java/util/ArrayList/add(Ljava/lang/Object;)Z
		pop
		aload 8
		new java/util/ArrayList
		dup
		invokespecial java/util/ArrayList/<init>()V
		astore 9
		aload 9
		ldc ""
		invokevirtual java/util/ArrayList/add(Ljava/lang/Object;)Z
		pop
		aload 9
		ldc 0
		invokestatic java/lang/Integer/valueOf(I)Ljava/lang/Integer;
		invokevirtual java/util/ArrayList/add(Ljava/lang/Object;)Z
		pop
		new List
		dup
		aload 9
		invokespecial List/<init>(Ljava/util/ArrayList;)V
		invokevirtual java/util/ArrayList/add(Ljava/lang/Object;)Z
		pop
		aload 8
		new java/util/ArrayList
		dup
		invokespecial java/util/ArrayList/<init>()V
		astore 9
		aload 9
		ldc ""
		invokevirtual java/util/ArrayList/add(Ljava/lang/Object;)Z
		pop
		aload 9
		ldc 0
		invokestatic java/lang/Integer/valueOf(I)Ljava/lang/Integer;
		invokevirtual java/util/ArrayList/add(Ljava/lang/Object;)Z
		pop
		new List
		dup
		aload 9
		invokespecial List/<init>(Ljava/util/ArrayList;)V
		invokevirtual java/util/ArrayList/add(Ljava/lang/Object;)Z
		pop
		aload 8
		new java/util/ArrayList
		dup
		invokespecial java/util/ArrayList/<init>()V
		astore 9
		aload 9
		ldc ""
		invokevirtual java/util/ArrayList/add(Ljava/lang/Object;)Z
		pop
		aload 9
		ldc 0
		invokestatic java/lang/Integer/valueOf(I)Ljava/lang/Integer;
		invokevirtual java/util/ArrayList/add(Ljava/lang/Object;)Z
		pop
		new List
		dup
		aload 9
		invokespecial List/<init>(Ljava/util/ArrayList;)V
		invokevirtual java/util/ArrayList/add(Ljava/lang/Object;)Z
		pop
		aload 8
		new java/util/ArrayList
		dup
		invokespecial java/util/ArrayList/<init>()V
		astore 9
		aload 9
		ldc ""
		invokevirtual java/util/ArrayList/add(Ljava/lang/Object;)Z
		pop
		aload 9
		ldc 0
		invokestatic java/lang/Integer/valueOf(I)Ljava/lang/Integer;
		invokevirtual java/util/ArrayList/add(Ljava/lang/Object;)Z
		pop
		new List
		dup
		aload 9
		invokespecial List/<init>(Ljava/util/ArrayList;)V
		invokevirtual java/util/ArrayList/add(Ljava/lang/Object;)Z
		pop
		aload 8
		new java/util/ArrayList
		dup
		invokespecial java/util/ArrayList/<init>()V
		astore 9
		aload 9
		ldc ""
		invokevirtual java/util/ArrayList/add(Ljava/lang/Object;)Z
		pop
		aload 9
		ldc 0
		invokestatic java/lang/Integer/valueOf(I)Ljava/lang/Integer;
		invokevirtual java/util/ArrayList/add(Ljava/lang/Object;)Z
		pop
		new List
		dup
		aload 9
		invokespecial List/<init>(Ljava/util/ArrayList;)V
		invokevirtual java/util/ArrayList/add(Ljava/lang/Object;)Z
		pop
		aload 8
		new java/util/ArrayList
		dup
		invokespecial java/util/ArrayList/<init>()V
		astore 9
		aload 9
		ldc ""
		invokevirtual java/util/ArrayList/add(Ljava/lang/Object;)Z
		pop
		aload 9
		ldc 0
		invokestatic java/lang/Integer/valueOf(I)Ljava/lang/Integer;
		invokevirtual java/util/ArrayList/add(Ljava/lang/Object;)Z
		pop
		new List
		dup
		aload 9
		invokespecial List/<init>(Ljava/util/ArrayList;)V
		invokevirtual java/util/ArrayList/add(Ljava/lang/Object;)Z
		pop
		aload 8
		new java/util/ArrayList
		dup
		invokespecial java/util/ArrayList/<init>()V
		astore 9
		aload 9
		ldc ""
		invokevirtual java/util/ArrayList/add(Ljava/lang/Object;)Z
		pop
		aload 9
		ldc 0
		invokestatic java/lang/Integer/valueOf(I)Ljava/lang/Integer;
		invokevirtual java/util/ArrayList/add(Ljava/lang/Object;)Z
		pop
		new List
		dup
		aload 9
		invokespecial List/<init>(Ljava/util/ArrayList;)V
		invokevirtual java/util/ArrayList/add(Ljava/lang/Object;)Z
		pop
		aload 8
		new java/util/ArrayList
		dup
		invokespecial java/util/ArrayList/<init>()V
		astore 9
		aload 9
		ldc ""
		invokevirtual java/util/ArrayList/add(Ljava/lang/Object;)Z
		pop
		aload 9
		ldc 0
		invokestatic java/lang/Integer/valueOf(I)Ljava/lang/Integer;
		invokevirtual java/util/ArrayList/add(Ljava/lang/Object;)Z
		pop
		new List
		dup
		aload 9
		invokespecial List/<init>(Ljava/util/ArrayList;)V
		invokevirtual java/util/ArrayList/add(Ljava/lang/Object;)Z
		pop
		aload 8
		new java/util/ArrayList
		dup
		invokespecial java/util/ArrayList/<init>()V
		astore 9
		aload 9
		ldc ""
		invokevirtual java/util/ArrayList/add(Ljava/lang/Object;)Z
		pop
		aload 9
		ldc 0
		invokestatic java/lang/Integer/valueOf(I)Ljava/lang/Integer;
		invokevirtual java/util/ArrayList/add(Ljava/lang/Object;)Z
		pop
		new List
		dup
		aload 9
		invokespecial List/<init>(Ljava/util/ArrayList;)V
		invokevirtual java/util/ArrayList/add(Ljava/lang/Object;)Z
		pop
		aload 8
		new java/util/ArrayList
		dup
		invokespecial java/util/ArrayList/<init>()V
		astore 9
		aload 9
		ldc ""
		invokevirtual java/util/ArrayList/add(Ljava/lang/Object;)Z
		pop
		aload 9
		ldc 0
		invokestatic java/lang/Integer/valueOf(I)Ljava/lang/Integer;
		invokevirtual java/util/ArrayList/add(Ljava/lang/Object;)Z
		pop
		new List
		dup
		aload 9
		invokespecial List/<init>(Ljava/util/ArrayList;)V
		invokevirtual java/util/ArrayList/add(Ljava/lang/Object;)Z
		pop
		aload 8
		new java/util/ArrayList
		dup
		invokespecial java/util/ArrayList/<init>()V
		astore 9
		aload 9
		ldc ""
		invokevirtual java/util/ArrayList/add(Ljava/lang/Object;)Z
		pop
		aload 9
		ldc 0
		invokestatic java/lang/Integer/valueOf(I)Ljava/lang/Integer;
		invokevirtual java/util/ArrayList/add(Ljava/lang/Object;)Z
		pop
		new List
		dup
		aload 9
		invokespecial List/<init>(Ljava/util/ArrayList;)V
		invokevirtual java/util/ArrayList/add(Ljava/lang/Object;)Z
		pop
		aload 8
		new java/util/ArrayList
		dup
		invokespecial java/util/ArrayList/<init>()V
		astore 9
		aload 9
		ldc ""
		invokevirtual java/util/ArrayList/add(Ljava/lang/Object;)Z
		pop
		aload 9
		ldc 0
		invokestatic java/lang/Integer/valueOf(I)Ljava/lang/Integer;
		invokevirtual java/util/ArrayList/add(Ljava/lang/Object;)Z
		pop
		new List
		dup
		aload 9
		invokespecial List/<init>(Ljava/util/ArrayList;)V
		invokevirtual java/util/ArrayList/add(Ljava/lang/Object;)Z
		pop
		aload 8
		new java/util/ArrayList
		dup
		invokespecial java/util/ArrayList/<init>()V
		astore 9
		aload 9
		ldc ""
		invokevirtual java/util/ArrayList/add(Ljava/lang/Object;)Z
		pop
		aload 9
		ldc 0
		invokestatic java/lang/Integer/valueOf(I)Ljava/lang/Integer;
		invokevirtual java/util/ArrayList/add(Ljava/lang/Object;)Z
		pop
		new List
		dup
		aload 9
		invokespecial List/<init>(Ljava/util/ArrayList;)V
		invokevirtual java/util/ArrayList/add(Ljava/lang/Object;)Z
		pop
		aload 8
		new java/util/ArrayList
		dup
		invokespecial java/util/ArrayList/<init>()V
		astore 9
		aload 9
		ldc ""
		invokevirtual java/util/ArrayList/add(Ljava/lang/Object;)Z
		pop
		aload 9
		ldc 0
		invokestatic java/lang/Integer/valueOf(I)Ljava/lang/Integer;
		invokevirtual java/util/ArrayList/add(Ljava/lang/Object;)Z
		pop
		new List
		dup
		aload 9
		invokespecial List/<init>(Ljava/util/ArrayList;)V
		invokevirtual java/util/ArrayList/add(Ljava/lang/Object;)Z
		pop
		aload 8
		new java/util/ArrayList
		dup
		invokespecial java/util/ArrayList/<init>()V
		astore 9
		aload 9
		ldc ""
		invokevirtual java/util/ArrayList/add(Ljava/lang/Object;)Z
		pop
		aload 9
		ldc 0
		invokestatic java/lang/Integer/valueOf(I)Ljava/lang/Integer;
		invokevirtual java/util/ArrayList/add(Ljava/lang/Object;)Z
		pop
		new List
		dup
		aload 9
		invokespecial List/<init>(Ljava/util/ArrayList;)V
		invokevirtual java/util/ArrayList/add(Ljava/lang/Object;)Z
		pop
		aload 8
		new java/util/ArrayList
		dup
		invokespecial java/util/ArrayList/<init>()V
		astore 9
		aload 9
		ldc ""
		invokevirtual java/util/ArrayList/add(Ljava/lang/Object;)Z
		pop
		aload 9
		ldc 0
		invokestatic java/lang/Integer/valueOf(I)Ljava/lang/Integer;
		invokevirtual java/util/ArrayList/add(Ljava/lang/Object;)Z
		pop
		new List
		dup
		aload 9
		invokespecial List/<init>(Ljava/util/ArrayList;)V
		invokevirtual java/util/ArrayList/add(Ljava/lang/Object;)Z
		pop
		aload 8
		new java/util/ArrayList
		dup
		invokespecial java/util/ArrayList/<init>()V
		astore 9
		aload 9
		ldc ""
		invokevirtual java/util/ArrayList/add(Ljava/lang/Object;)Z
		pop
		aload 9
		ldc 0
		invokestatic java/lang/Integer/valueOf(I)Ljava/lang/Integer;
		invokevirtual java/util/ArrayList/add(Ljava/lang/Object;)Z
		pop
		new List
		dup
		aload 9
		invokespecial List/<init>(Ljava/util/ArrayList;)V
		invokevirtual java/util/ArrayList/add(Ljava/lang/Object;)Z
		pop
		aload 8
		new java/util/ArrayList
		dup
		invokespecial java/util/ArrayList/<init>()V
		astore 9
		aload 9
		ldc ""
		invokevirtual java/util/ArrayList/add(Ljava/lang/Object;)Z
		pop
		aload 9
		ldc 0
		invokestatic java/lang/Integer/valueOf(I)Ljava/lang/Integer;
		invokevirtual java/util/ArrayList/add(Ljava/lang/Object;)Z
		pop
		new List
		dup
		aload 9
		invokespecial List/<init>(Ljava/util/ArrayList;)V
		invokevirtual java/util/ArrayList/add(Ljava/lang/Object;)Z
		pop
		aload 8
		new java/util/ArrayList
		dup
		invokespecial java/util/ArrayList/<init>()V
		astore 9
		aload 9
		ldc ""
		invokevirtual java/util/ArrayList/add(Ljava/lang/Object;)Z
		pop
		aload 9
		ldc 0
		invokestatic java/lang/Integer/valueOf(I)Ljava/lang/Integer;
		invokevirtual java/util/ArrayList/add(Ljava/lang/Object;)Z
		pop
		new List
		dup
		aload 9
		invokespecial List/<init>(Ljava/util/ArrayList;)V
		invokevirtual java/util/ArrayList/add(Ljava/lang/Object;)Z
		pop
		aload 8
		new java/util/ArrayList
		dup
		invokespecial java/util/ArrayList/<init>()V
		astore 9
		aload 9
		ldc ""
		invokevirtual java/util/ArrayList/add(Ljava/lang/Object;)Z
		pop
		aload 9
		ldc 0
		invokestatic java/lang/Integer/valueOf(I)Ljava/lang/Integer;
		invokevirtual java/util/ArrayList/add(Ljava/lang/Object;)Z
		pop
		new List
		dup
		aload 9
		invokespecial List/<init>(Ljava/util/ArrayList;)V
		invokevirtual java/util/ArrayList/add(Ljava/lang/Object;)Z
		pop
		aload 8
		new java/util/ArrayList
		dup
		invokespecial java/util/ArrayList/<init>()V
		astore 9
		aload 9
		ldc ""
		invokevirtual java/util/ArrayList/add(Ljava/lang/Object;)Z
		pop
		aload 9
		ldc 0
		invokestatic java/lang/Integer/valueOf(I)Ljava/lang/Integer;
		invokevirtual java/util/ArrayList/add(Ljava/lang/Object;)Z
		pop
		new List
		dup
		aload 9
		invokespecial List/<init>(Ljava/util/ArrayList;)V
		invokevirtual java/util/ArrayList/add(Ljava/lang/Object;)Z
		pop
		aload 8
		new java/util/ArrayList
		dup
		invokespecial java/util/ArrayList/<init>()V
		astore 9
		aload 9
		ldc ""
		invokevirtual java/util/ArrayList/add(Ljava/lang/Object;)Z
		pop
		aload 9
		ldc 0
		invokestatic java/lang/Integer/valueOf(I)Ljava/lang/Integer;
		invokevirtual java/util/ArrayList/add(Ljava/lang/Object;)Z
		pop
		new List
		dup
		aload 9
		invokespecial List/<init>(Ljava/util/ArrayList;)V
		invokevirtual java/util/ArrayList/add(Ljava/lang/Object;)Z
		pop
		aload 8
		new java/util/ArrayList
		dup
		invokespecial java/util/ArrayList/<init>()V
		astore 9
		aload 9
		ldc ""
		invokevirtual java/util/ArrayList/add(Ljava/lang/Object;)Z
		pop
		aload 9
		ldc 0
		invokestatic java/lang/Integer/valueOf(I)Ljava/lang/Integer;
		invokevirtual java/util/ArrayList/add(Ljava/lang/Object;)Z
		pop
		new List
		dup
		aload 9
		invokespecial List/<init>(Ljava/util/ArrayList;)V
		invokevirtual java/util/ArrayList/add(Ljava/lang/Object;)Z
		pop
		aload 8
		new java/util/ArrayList
		dup
		invokespecial java/util/ArrayList/<init>()V
		astore 9
		aload 9
		ldc ""
		invokevirtual java/util/ArrayList/add(Ljava/lang/Object;)Z
		pop
		aload 9
		ldc 0
		invokestatic java/lang/Integer/valueOf(I)Ljava/lang/Integer;
		invokevirtual java/util/ArrayList/add(Ljava/lang/Object;)Z
		pop
		new List
		dup
		aload 9
		invokespecial List/<init>(Ljava/util/ArrayList;)V
		invokevirtual java/util/ArrayList/add(Ljava/lang/Object;)Z
		pop
		aload 8
		new java/util/ArrayList
		dup
		invokespecial java/util/ArrayList/<init>()V
		astore 9
		aload 9
		ldc ""
		invokevirtual java/util/ArrayList/add(Ljava/lang/Object;)Z
		pop
		aload 9
		ldc 0
		invokestatic java/lang/Integer/valueOf(I)Ljava/lang/Integer;
		invokevirtual java/util/ArrayList/add(Ljava/lang/Object;)Z
		pop
		new List
		dup
		aload 9
		invokespecial List/<init>(Ljava/util/ArrayList;)V
		invokevirtual java/util/ArrayList/add(Ljava/lang/Object;)Z
		pop
		aload 8
		new java/util/ArrayList
		dup
		invokespecial java/util/ArrayList/<init>()V
		astore 9
		aload 9
		ldc ""
		invokevirtual java/util/ArrayList/add(Ljava/lang/Object;)Z
		pop
		aload 9
		ldc 0
		invokestatic java/lang/Integer/valueOf(I)Ljava/lang/Integer;
		invokevirtual java/util/ArrayList/add(Ljava/lang/Object;)Z
		pop
		new List
		dup
		aload 9
		invokespecial List/<init>(Ljava/util/ArrayList;)V
		invokevirtual java/util/ArrayList/add(Ljava/lang/Object;)Z
		pop
		aload 8
		new java/util/ArrayList
		dup
		invokespecial java/util/ArrayList/<init>()V
		astore 9
		aload 9
		ldc ""
		invokevirtual java/util/ArrayList/add(Ljava/lang/Object;)Z
		pop
		aload 9
		ldc 0
		invokestatic java/lang/Integer/valueOf(I)Ljava/lang/Integer;
		invokevirtual java/util/ArrayList/add(Ljava/lang/Object;)Z
		pop
		new List
		dup
		aload 9
		invokespecial List/<init>(Ljava/util/ArrayList;)V
		invokevirtual java/util/ArrayList/add(Ljava/lang/Object;)Z
		pop
		aload 8
		new java/util/ArrayList
		dup
		invokespecial java/util/ArrayList/<init>()V
		astore 9
		aload 9
		ldc ""
		invokevirtual java/util/ArrayList/add(Ljava/lang/Object;)Z
		pop
		aload 9
		ldc 0
		invokestatic java/lang/Integer/valueOf(I)Ljava/lang/Integer;
		invokevirtual java/util/ArrayList/add(Ljava/lang/Object;)Z
		pop
		new List
		dup
		aload 9
		invokespecial List/<init>(Ljava/util/ArrayList;)V
		invokevirtual java/util/ArrayList/add(Ljava/lang/Object;)Z
		pop
		aload 8
		new java/util/ArrayList
		dup
		invokespecial java/util/ArrayList/<init>()V
		astore 9
		aload 9
		ldc ""
		invokevirtual java/util/ArrayList/add(Ljava/lang/Object;)Z
		pop
		aload 9
		ldc 0
		invokestatic java/lang/Integer/valueOf(I)Ljava/lang/Integer;
		invokevirtual java/util/ArrayList/add(Ljava/lang/Object;)Z
		pop
		new List
		dup
		aload 9
		invokespecial List/<init>(Ljava/util/ArrayList;)V
		invokevirtual java/util/ArrayList/add(Ljava/lang/Object;)Z
		pop
		aload 8
		new java/util/ArrayList
		dup
		invokespecial java/util/ArrayList/<init>()V
		astore 9
		aload 9
		ldc ""
		invokevirtual java/util/ArrayList/add(Ljava/lang/Object;)Z
		pop
		aload 9
		ldc 0
		invokestatic java/lang/Integer/valueOf(I)Ljava/lang/Integer;
		invokevirtual java/util/ArrayList/add(Ljava/lang/Object;)Z
		pop
		new List
		dup
		aload 9
		invokespecial List/<init>(Ljava/util/ArrayList;)V
		invokevirtual java/util/ArrayList/add(Ljava/lang/Object;)Z
		pop
		aload 8
		new java/util/ArrayList
		dup
		invokespecial java/util/ArrayList/<init>()V
		astore 9
		aload 9
		ldc ""
		invokevirtual java/util/ArrayList/add(Ljava/lang/Object;)Z
		pop
		aload 9
		ldc 0
		invokestatic java/lang/Integer/valueOf(I)Ljava/lang/Integer;
		invokevirtual java/util/ArrayList/add(Ljava/lang/Object;)Z
		pop
		new List
		dup
		aload 9
		invokespecial List/<init>(Ljava/util/ArrayList;)V
		invokevirtual java/util/ArrayList/add(Ljava/lang/Object;)Z
		pop
		aload 8
		new java/util/ArrayList
		dup
		invokespecial java/util/ArrayList/<init>()V
		astore 9
		aload 9
		ldc ""
		invokevirtual java/util/ArrayList/add(Ljava/lang/Object;)Z
		pop
		aload 9
		ldc 0
		invokestatic java/lang/Integer/valueOf(I)Ljava/lang/Integer;
		invokevirtual java/util/ArrayList/add(Ljava/lang/Object;)Z
		pop
		new List
		dup
		aload 9
		invokespecial List/<init>(Ljava/util/ArrayList;)V
		invokevirtual java/util/ArrayList/add(Ljava/lang/Object;)Z
		pop
		aload 8
		new java/util/ArrayList
		dup
		invokespecial java/util/ArrayList/<init>()V
		astore 9
		aload 9
		ldc ""
		invokevirtual java/util/ArrayList/add(Ljava/lang/Object;)Z
		pop
		aload 9
		ldc 0
		invokestatic java/lang/Integer/valueOf(I)Ljava/lang/Integer;
		invokevirtual java/util/ArrayList/add(Ljava/lang/Object;)Z
		pop
		new List
		dup
		aload 9
		invokespecial List/<init>(Ljava/util/ArrayList;)V
		invokevirtual java/util/ArrayList/add(Ljava/lang/Object;)Z
		pop
		aload 8
		new java/util/ArrayList
		dup
		invokespecial java/util/ArrayList/<init>()V
		astore 9
		aload 9
		ldc ""
		invokevirtual java/util/ArrayList/add(Ljava/lang/Object;)Z
		pop
		aload 9
		ldc 0
		invokestatic java/lang/Integer/valueOf(I)Ljava/lang/Integer;
		invokevirtual java/util/ArrayList/add(Ljava/lang/Object;)Z
		pop
		new List
		dup
		aload 9
		invokespecial List/<init>(Ljava/util/ArrayList;)V
		invokevirtual java/util/ArrayList/add(Ljava/lang/Object;)Z
		pop
		aload 8
		new java/util/ArrayList
		dup
		invokespecial java/util/ArrayList/<init>()V
		astore 9
		aload 9
		ldc ""
		invokevirtual java/util/ArrayList/add(Ljava/lang/Object;)Z
		pop
		aload 9
		ldc 0
		invokestatic java/lang/Integer/valueOf(I)Ljava/lang/Integer;
		invokevirtual java/util/ArrayList/add(Ljava/lang/Object;)Z
		pop
		new List
		dup
		aload 9
		invokespecial List/<init>(Ljava/util/ArrayList;)V
		invokevirtual java/util/ArrayList/add(Ljava/lang/Object;)Z
		pop
		aload 8
		new java/util/ArrayList
		dup
		invokespecial java/util/ArrayList/<init>()V
		astore 9
		aload 9
		ldc ""
		invokevirtual java/util/ArrayList/add(Ljava/lang/Object;)Z
		pop
		aload 9
		ldc 0
		invokestatic java/lang/Integer/valueOf(I)Ljava/lang/Integer;
		invokevirtual java/util/ArrayList/add(Ljava/lang/Object;)Z
		pop
		new List
		dup
		aload 9
		invokespecial List/<init>(Ljava/util/ArrayList;)V
		invokevirtual java/util/ArrayList/add(Ljava/lang/Object;)Z
		pop
		aload 8
		new java/util/ArrayList
		dup
		invokespecial java/util/ArrayList/<init>()V
		astore 9
		aload 9
		ldc ""
		invokevirtual java/util/ArrayList/add(Ljava/lang/Object;)Z
		pop
		aload 9
		ldc 0
		invokestatic java/lang/Integer/valueOf(I)Ljava/lang/Integer;
		invokevirtual java/util/ArrayList/add(Ljava/lang/Object;)Z
		pop
		new List
		dup
		aload 9
		invokespecial List/<init>(Ljava/util/ArrayList;)V
		invokevirtual java/util/ArrayList/add(Ljava/lang/Object;)Z
		pop
		aload 8
		new java/util/ArrayList
		dup
		invokespecial java/util/ArrayList/<init>()V
		astore 9
		aload 9
		ldc ""
		invokevirtual java/util/ArrayList/add(Ljava/lang/Object;)Z
		pop
		aload 9
		ldc 0
		invokestatic java/lang/Integer/valueOf(I)Ljava/lang/Integer;
		invokevirtual java/util/ArrayList/add(Ljava/lang/Object;)Z
		pop
		new List
		dup
		aload 9
		invokespecial List/<init>(Ljava/util/ArrayList;)V
		invokevirtual java/util/ArrayList/add(Ljava/lang/Object;)Z
		pop
		aload 8
		new java/util/ArrayList
		dup
		invokespecial java/util/ArrayList/<init>()V
		astore 9
		aload 9
		ldc ""
		invokevirtual java/util/ArrayList/add(Ljava/lang/Object;)Z
		pop
		aload 9
		ldc 0
		invokestatic java/lang/Integer/valueOf(I)Ljava/lang/Integer;
		invokevirtual java/util/ArrayList/add(Ljava/lang/Object;)Z
		pop
		new List
		dup
		aload 9
		invokespecial List/<init>(Ljava/util/ArrayList;)V
		invokevirtual java/util/ArrayList/add(Ljava/lang/Object;)Z
		pop
		aload 8
		new java/util/ArrayList
		dup
		invokespecial java/util/ArrayList/<init>()V
		astore 9
		aload 9
		ldc ""
		invokevirtual java/util/ArrayList/add(Ljava/lang/Object;)Z
		pop
		aload 9
		ldc 0
		invokestatic java/lang/Integer/valueOf(I)Ljava/lang/Integer;
		invokevirtual java/util/ArrayList/add(Ljava/lang/Object;)Z
		pop
		new List
		dup
		aload 9
		invokespecial List/<init>(Ljava/util/ArrayList;)V
		invokevirtual java/util/ArrayList/add(Ljava/lang/Object;)Z
		pop
		aload 8
		new java/util/ArrayList
		dup
		invokespecial java/util/ArrayList/<init>()V
		astore 9
		aload 9
		ldc ""
		invokevirtual java/util/ArrayList/add(Ljava/lang/Object;)Z
		pop
		aload 9
		ldc 0
		invokestatic java/lang/Integer/valueOf(I)Ljava/lang/Integer;
		invokevirtual java/util/ArrayList/add(Ljava/lang/Object;)Z
		pop
		new List
		dup
		aload 9
		invokespecial List/<init>(Ljava/util/ArrayList;)V
		invokevirtual java/util/ArrayList/add(Ljava/lang/Object;)Z
		pop
		aload 8
		new java/util/ArrayList
		dup
		invokespecial java/util/ArrayList/<init>()V
		astore 9
		aload 9
		ldc ""
		invokevirtual java/util/ArrayList/add(Ljava/lang/Object;)Z
		pop
		aload 9
		ldc 0
		invokestatic java/lang/Integer/valueOf(I)Ljava/lang/Integer;
		invokevirtual java/util/ArrayList/add(Ljava/lang/Object;)Z
		pop
		new List
		dup
		aload 9
		invokespecial List/<init>(Ljava/util/ArrayList;)V
		invokevirtual java/util/ArrayList/add(Ljava/lang/Object;)Z
		pop
		aload 8
		new java/util/ArrayList
		dup
		invokespecial java/util/ArrayList/<init>()V
		astore 9
		aload 9
		ldc ""
		invokevirtual java/util/ArrayList/add(Ljava/lang/Object;)Z
		pop
		aload 9
		ldc 0
		invokestatic java/lang/Integer/valueOf(I)Ljava/lang/Integer;
		invokevirtual java/util/ArrayList/add(Ljava/lang/Object;)Z
		pop
		new List
		dup
		aload 9
		invokespecial List/<init>(Ljava/util/ArrayList;)V
		invokevirtual java/util/ArrayList/add(Ljava/lang/Object;)Z
		pop
		aload 8
		new java/util/ArrayList
		dup
		invokespecial java/util/ArrayList/<init>()V
		astore 9
		aload 9
		ldc ""
		invokevirtual java/util/ArrayList/add(Ljava/lang/Object;)Z
		pop
		aload 9
		ldc 0
		invokestatic java/lang/Integer/valueOf(I)Ljava/lang/Integer;
		invokevirtual java/util/ArrayList/add(Ljava/lang/Object;)Z
		pop
		new List
		dup
		aload 9
		invokespecial List/<init>(Ljava/util/ArrayList;)V
		invokevirtual java/util/ArrayList/add(Ljava/lang/Object;)Z
		pop
		aload 8
		new java/util/ArrayList
		dup
		invokespecial java/util/ArrayList/<init>()V
		astore 9
		aload 9
		ldc ""
		invokevirtual java/util/ArrayList/add(Ljava/lang/Object;)Z
		pop
		aload 9
		ldc 0
		invokestatic java/lang/Integer/valueOf(I)Ljava/lang/Integer;
		invokevirtual java/util/ArrayList/add(Ljava/lang/Object;)Z
		pop
		new List
		dup
		aload 9
		invokespecial List/<init>(Ljava/util/ArrayList;)V
		invokevirtual java/util/ArrayList/add(Ljava/lang/Object;)Z
		pop
		aload 8
		new java/util/ArrayList
		dup
		invokespecial java/util/ArrayList/<init>()V
		astore 9
		aload 9
		ldc ""
		invokevirtual java/util/ArrayList/add(Ljava/lang/Object;)Z
		pop
		aload 9
		ldc 0
		invokestatic java/lang/Integer/valueOf(I)Ljava/lang/Integer;
		invokevirtual java/util/ArrayList/add(Ljava/lang/Object;)Z
		pop
		new List
		dup
		aload 9
		invokespecial List/<init>(Ljava/util/ArrayList;)V
		invokevirtual java/util/ArrayList/add(Ljava/lang/Object;)Z
		pop
		aload 8
		new java/util/ArrayList
		dup
		invokespecial java/util/ArrayList/<init>()V
		astore 9
		aload 9
		ldc ""
		invokevirtual java/util/ArrayList/add(Ljava/lang/Object;)Z
		pop
		aload 9
		ldc 0
		invokestatic java/lang/Integer/valueOf(I)Ljava/lang/Integer;
		invokevirtual java/util/ArrayList/add(Ljava/lang/Object;)Z
		pop
		new List
		dup
		aload 9
		invokespecial List/<init>(Ljava/util/ArrayList;)V
		invokevirtual java/util/ArrayList/add(Ljava/lang/Object;)Z
		pop
		aload 8
		new java/util/ArrayList
		dup
		invokespecial java/util/ArrayList/<init>()V
		astore 9
		aload 9
		ldc ""
		invokevirtual java/util/ArrayList/add(Ljava/lang/Object;)Z
		pop
		aload 9
		ldc 0
		invokestatic java/lang/Integer/valueOf(I)Ljava/lang/Integer;
		invokevirtual java/util/ArrayList/add(Ljava/lang/Object;)Z
		pop
		new List
		dup
		aload 9
		invokespecial List/<init>(Ljava/util/ArrayList;)V
		invokevirtual java/util/ArrayList/add(Ljava/lang/Object;)Z
		pop
		aload 8
		new java/util/ArrayList
		dup
		invokespecial java/util/ArrayList/<init>()V
		astore 9
		aload 9
		ldc ""
		invokevirtual java/util/ArrayList/add(Ljava/lang/Object;)Z
		pop
		aload 9
		ldc 0
		invokestatic java/lang/Integer/valueOf(I)Ljava/lang/Integer;
		invokevirtual java/util/ArrayList/add(Ljava/lang/Object;)Z
		pop
		new List
		dup
		aload 9
		invokespecial List/<init>(Ljava/util/ArrayList;)V
		invokevirtual java/util/ArrayList/add(Ljava/lang/Object;)Z
		pop
		aload 8
		new java/util/ArrayList
		dup
		invokespecial java/util/ArrayList/<init>()V
		astore 9
		aload 9
		ldc ""
		invokevirtual java/util/ArrayList/add(Ljava/lang/Object;)Z
		pop
		aload 9
		ldc 0
		invokestatic java/lang/Integer/valueOf(I)Ljava/lang/Integer;
		invokevirtual java/util/ArrayList/add(Ljava/lang/Object;)Z
		pop
		new List
		dup
		aload 9
		invokespecial List/<init>(Ljava/util/ArrayList;)V
		invokevirtual java/util/ArrayList/add(Ljava/lang/Object;)Z
		pop
		aload 8
		new java/util/ArrayList
		dup
		invokespecial java/util/ArrayList/<init>()V
		astore 9
		aload 9
		ldc ""
		invokevirtual java/util/ArrayList/add(Ljava/lang/Object;)Z
		pop
		aload 9
		ldc 0
		invokestatic java/lang/Integer/valueOf(I)Ljava/lang/Integer;
		invokevirtual java/util/ArrayList/add(Ljava/lang/Object;)Z
		pop
		new List
		dup
		aload 9
		invokespecial List/<init>(Ljava/util/ArrayList;)V
		invokevirtual java/util/ArrayList/add(Ljava/lang/Object;)Z
		pop
		aload 8
		new java/util/ArrayList
		dup
		invokespecial java/util/ArrayList/<init>()V
		astore 9
		aload 9
		ldc ""
		invokevirtual java/util/ArrayList/add(Ljava/lang/Object;)Z
		pop
		aload 9
		ldc 0
		invokestatic java/lang/Integer/valueOf(I)Ljava/lang/Integer;
		invokevirtual java/util/ArrayList/add(Ljava/lang/Object;)Z
		pop
		new List
		dup
		aload 9
		invokespecial List/<init>(Ljava/util/ArrayList;)V
		invokevirtual java/util/ArrayList/add(Ljava/lang/Object;)Z
		pop
		aload 8
		new java/util/ArrayList
		dup
		invokespecial java/util/ArrayList/<init>()V
		astore 9
		aload 9
		ldc ""
		invokevirtual java/util/ArrayList/add(Ljava/lang/Object;)Z
		pop
		aload 9
		ldc 0
		invokestatic java/lang/Integer/valueOf(I)Ljava/lang/Integer;
		invokevirtual java/util/ArrayList/add(Ljava/lang/Object;)Z
		pop
		new List
		dup
		aload 9
		invokespecial List/<init>(Ljava/util/ArrayList;)V
		invokevirtual java/util/ArrayList/add(Ljava/lang/Object;)Z
		pop
		aload 8
		new java/util/ArrayList
		dup
		invokespecial java/util/ArrayList/<init>()V
		astore 9
		aload 9
		ldc ""
		invokevirtual java/util/ArrayList/add(Ljava/lang/Object;)Z
		pop
		aload 9
		ldc 0
		invokestatic java/lang/Integer/valueOf(I)Ljava/lang/Integer;
		invokevirtual java/util/ArrayList/add(Ljava/lang/Object;)Z
		pop
		new List
		dup
		aload 9
		invokespecial List/<init>(Ljava/util/ArrayList;)V
		invokevirtual java/util/ArrayList/add(Ljava/lang/Object;)Z
		pop
		aload 8
		new java/util/ArrayList
		dup
		invokespecial java/util/ArrayList/<init>()V
		astore 9
		aload 9
		ldc ""
		invokevirtual java/util/ArrayList/add(Ljava/lang/Object;)Z
		pop
		aload 9
		ldc 0
		invokestatic java/lang/Integer/valueOf(I)Ljava/lang/Integer;
		invokevirtual java/util/ArrayList/add(Ljava/lang/Object;)Z
		pop
		new List
		dup
		aload 9
		invokespecial List/<init>(Ljava/util/ArrayList;)V
		invokevirtual java/util/ArrayList/add(Ljava/lang/Object;)Z
		pop
		aload 8
		new java/util/ArrayList
		dup
		invokespecial java/util/ArrayList/<init>()V
		astore 9
		aload 9
		ldc ""
		invokevirtual java/util/ArrayList/add(Ljava/lang/Object;)Z
		pop
		aload 9
		ldc 0
		invokestatic java/lang/Integer/valueOf(I)Ljava/lang/Integer;
		invokevirtual java/util/ArrayList/add(Ljava/lang/Object;)Z
		pop
		new List
		dup
		aload 9
		invokespecial List/<init>(Ljava/util/ArrayList;)V
		invokevirtual java/util/ArrayList/add(Ljava/lang/Object;)Z
		pop
		aload 8
		new java/util/ArrayList
		dup
		invokespecial java/util/ArrayList/<init>()V
		astore 9
		aload 9
		ldc ""
		invokevirtual java/util/ArrayList/add(Ljava/lang/Object;)Z
		pop
		aload 9
		ldc 0
		invokestatic java/lang/Integer/valueOf(I)Ljava/lang/Integer;
		invokevirtual java/util/ArrayList/add(Ljava/lang/Object;)Z
		pop
		new List
		dup
		aload 9
		invokespecial List/<init>(Ljava/util/ArrayList;)V
		invokevirtual java/util/ArrayList/add(Ljava/lang/Object;)Z
		pop
		aload 8
		new java/util/ArrayList
		dup
		invokespecial java/util/ArrayList/<init>()V
		astore 9
		aload 9
		ldc ""
		invokevirtual java/util/ArrayList/add(Ljava/lang/Object;)Z
		pop
		aload 9
		ldc 0
		invokestatic java/lang/Integer/valueOf(I)Ljava/lang/Integer;
		invokevirtual java/util/ArrayList/add(Ljava/lang/Object;)Z
		pop
		new List
		dup
		aload 9
		invokespecial List/<init>(Ljava/util/ArrayList;)V
		invokevirtual java/util/ArrayList/add(Ljava/lang/Object;)Z
		pop
		aload 8
		new java/util/ArrayList
		dup
		invokespecial java/util/ArrayList/<init>()V
		astore 9
		aload 9
		ldc ""
		invokevirtual java/util/ArrayList/add(Ljava/lang/Object;)Z
		pop
		aload 9
		ldc 0
		invokestatic java/lang/Integer/valueOf(I)Ljava/lang/Integer;
		invokevirtual java/util/ArrayList/add(Ljava/lang/Object;)Z
		pop
		new List
		dup
		aload 9
		invokespecial List/<init>(Ljava/util/ArrayList;)V
		invokevirtual java/util/ArrayList/add(Ljava/lang/Object;)Z
		pop
		aload 8
		new java/util/ArrayList
		dup
		invokespecial java/util/ArrayList/<init>()V
		astore 9
		aload 9
		ldc ""
		invokevirtual java/util/ArrayList/add(Ljava/lang/Object;)Z
		pop
		aload 9
		ldc 0
		invokestatic java/lang/Integer/valueOf(I)Ljava/lang/Integer;
		invokevirtual java/util/ArrayList/add(Ljava/lang/Object;)Z
		pop
		new List
		dup
		aload 9
		invokespecial List/<init>(Ljava/util/ArrayList;)V
		invokevirtual java/util/ArrayList/add(Ljava/lang/Object;)Z
		pop
		aload 8
		new java/util/ArrayList
		dup
		invokespecial java/util/ArrayList/<init>()V
		astore 9
		aload 9
		ldc ""
		invokevirtual java/util/ArrayList/add(Ljava/lang/Object;)Z
		pop
		aload 9
		ldc 0
		invokestatic java/lang/Integer/valueOf(I)Ljava/lang/Integer;
		invokevirtual java/util/ArrayList/add(Ljava/lang/Object;)Z
		pop
		new List
		dup
		aload 9
		invokespecial List/<init>(Ljava/util/ArrayList;)V
		invokevirtual java/util/ArrayList/add(Ljava/lang/Object;)Z
		pop
		aload 8
		new java/util/ArrayList
		dup
		invokespecial java/util/ArrayList/<init>()V
		astore 9
		aload 9
		ldc ""
		invokevirtual java/util/ArrayList/add(Ljava/lang/Object;)Z
		pop
		aload 9
		ldc 0
		invokestatic java/lang/Integer/valueOf(I)Ljava/lang/Integer;
		invokevirtual java/util/ArrayList/add(Ljava/lang/Object;)Z
		pop
		new List
		dup
		aload 9
		invokespecial List/<init>(Ljava/util/ArrayList;)V
		invokevirtual java/util/ArrayList/add(Ljava/lang/Object;)Z
		pop
		aload 8
		new java/util/ArrayList
		dup
		invokespecial java/util/ArrayList/<init>()V
		astore 9
		aload 9
		ldc ""
		invokevirtual java/util/ArrayList/add(Ljava/lang/Object;)Z
		pop
		aload 9
		ldc 0
		invokestatic java/lang/Integer/valueOf(I)Ljava/lang/Integer;
		invokevirtual java/util/ArrayList/add(Ljava/lang/Object;)Z
		pop
		new List
		dup
		aload 9
		invokespecial List/<init>(Ljava/util/ArrayList;)V
		invokevirtual java/util/ArrayList/add(Ljava/lang/Object;)Z
		pop
		aload 8
		new java/util/ArrayList
		dup
		invokespecial java/util/ArrayList/<init>()V
		astore 9
		aload 9
		ldc ""
		invokevirtual java/util/ArrayList/add(Ljava/lang/Object;)Z
		pop
		aload 9
		ldc 0
		invokestatic java/lang/Integer/valueOf(I)Ljava/lang/Integer;
		invokevirtual java/util/ArrayList/add(Ljava/lang/Object;)Z
		pop
		new List
		dup
		aload 9
		invokespecial List/<init>(Ljava/util/ArrayList;)V
		invokevirtual java/util/ArrayList/add(Ljava/lang/Object;)Z
		pop
		aload 8
		new java/util/ArrayList
		dup
		invokespecial java/util/ArrayList/<init>()V
		astore 9
		aload 9
		ldc ""
		invokevirtual java/util/ArrayList/add(Ljava/lang/Object;)Z
		pop
		aload 9
		ldc 0
		invokestatic java/lang/Integer/valueOf(I)Ljava/lang/Integer;
		invokevirtual java/util/ArrayList/add(Ljava/lang/Object;)Z
		pop
		new List
		dup
		aload 9
		invokespecial List/<init>(Ljava/util/ArrayList;)V
		invokevirtual java/util/ArrayList/add(Ljava/lang/Object;)Z
		pop
		aload 8
		new java/util/ArrayList
		dup
		invokespecial java/util/ArrayList/<init>()V
		astore 9
		aload 9
		ldc ""
		invokevirtual java/util/ArrayList/add(Ljava/lang/Object;)Z
		pop
		aload 9
		ldc 0
		invokestatic java/lang/Integer/valueOf(I)Ljava/lang/Integer;
		invokevirtual java/util/ArrayList/add(Ljava/lang/Object;)Z
		pop
		new List
		dup
		aload 9
		invokespecial List/<init>(Ljava/util/ArrayList;)V
		invokevirtual java/util/ArrayList/add(Ljava/lang/Object;)Z
		pop
		aload 8
		new java/util/ArrayList
		dup
		invokespecial java/util/ArrayList/<init>()V
		astore 9
		aload 9
		ldc ""
		invokevirtual java/util/ArrayList/add(Ljava/lang/Object;)Z
		pop
		aload 9
		ldc 0
		invokestatic java/lang/Integer/valueOf(I)Ljava/lang/Integer;
		invokevirtual java/util/ArrayList/add(Ljava/lang/Object;)Z
		pop
		new List
		dup
		aload 9
		invokespecial List/<init>(Ljava/util/ArrayList;)V
		invokevirtual java/util/ArrayList/add(Ljava/lang/Object;)Z
		pop
		aload 8
		new java/util/ArrayList
		dup
		invokespecial java/util/ArrayList/<init>()V
		astore 9
		aload 9
		ldc ""
		invokevirtual java/util/ArrayList/add(Ljava/lang/Object;)Z
		pop
		aload 9
		ldc 0
		invokestatic java/lang/Integer/valueOf(I)Ljava/lang/Integer;
		invokevirtual java/util/ArrayList/add(Ljava/lang/Object;)Z
		pop
		new List
		dup
		aload 9
		invokespecial List/<init>(Ljava/util/ArrayList;)V
		invokevirtual java/util/ArrayList/add(Ljava/lang/Object;)Z
		pop
		aload 8
		new java/util/ArrayList
		dup
		invokespecial java/util/ArrayList/<init>()V
		astore 9
		aload 9
		ldc ""
		invokevirtual java/util/ArrayList/add(Ljava/lang/Object;)Z
		pop
		aload 9
		ldc 0
		invokestatic java/lang/Integer/valueOf(I)Ljava/lang/Integer;
		invokevirtual java/util/ArrayList/add(Ljava/lang/Object;)Z
		pop
		new List
		dup
		aload 9
		invokespecial List/<init>(Ljava/util/ArrayList;)V
		invokevirtual java/util/ArrayList/add(Ljava/lang/Object;)Z
		pop
		aload 8
		new java/util/ArrayList
		dup
		invokespecial java/util/ArrayList/<init>()V
		astore 9
		aload 9
		ldc ""
		invokevirtual java/util/ArrayList/add(Ljava/lang/Object;)Z
		pop
		aload 9
		ldc 0
		invokestatic java/lang/Integer/valueOf(I)Ljava/lang/Integer;
		invokevirtual java/util/ArrayList/add(Ljava/lang/Object;)Z
		pop
		new List
		dup
		aload 9
		invokespecial List/<init>(Ljava/util/ArrayList;)V
		invokevirtual java/util/ArrayList/add(Ljava/lang/Object;)Z
		pop
		aload 8
		new java/util/ArrayList
		dup
		invokespecial java/util/ArrayList/<init>()V
		astore 9
		aload 9
		ldc ""
		invokevirtual java/util/ArrayList/add(Ljava/lang/Object;)Z
		pop
		aload 9
		ldc 0
		invokestatic java/lang/Integer/valueOf(I)Ljava/lang/Integer;
		invokevirtual java/util/ArrayList/add(Ljava/lang/Object;)Z
		pop
		new List
		dup
		aload 9
		invokespecial List/<init>(Ljava/util/ArrayList;)V
		invokevirtual java/util/ArrayList/add(Ljava/lang/Object;)Z
		pop
		aload 8
		new java/util/ArrayList
		dup
		invokespecial java/util/ArrayList/<init>()V
		astore 9
		aload 9
		ldc ""
		invokevirtual java/util/ArrayList/add(Ljava/lang/Object;)Z
		pop
		aload 9
		ldc 0
		invokestatic java/lang/Integer/valueOf(I)Ljava/lang/Integer;
		invokevirtual java/util/ArrayList/add(Ljava/lang/Object;)Z
		pop
		new List
		dup
		aload 9
		invokespecial List/<init>(Ljava/util/ArrayList;)V
		invokevirtual java/util/ArrayList/add(Ljava/lang/Object;)Z
		pop
		aload 8
		new java/util/ArrayList
		dup
		invokespecial java/util/ArrayList/<init>()V
		astore 9
		aload 9
		ldc ""
		invokevirtual java/util/ArrayList/add(Ljava/lang/Object;)Z
		pop
		aload 9
		ldc 0
		invokestatic java/lang/Integer/valueOf(I)Ljava/lang/Integer;
		invokevirtual java/util/ArrayList/add(Ljava/lang/Object;)Z
		pop
		new List
		dup
		aload 9
		invokespecial List/<init>(Ljava/util/ArrayList;)V
		invokevirtual java/util/ArrayList/add(Ljava/lang/Object;)Z
		pop
		aload 8
		new java/util/ArrayList
		dup
		invokespecial java/util/ArrayList/<init>()V
		astore 9
		aload 9
		ldc ""
		invokevirtual java/util/ArrayList/add(Ljava/lang/Object;)Z
		pop
		aload 9
		ldc 0
		invokestatic java/lang/Integer/valueOf(I)Ljava/lang/Integer;
		invokevirtual java/util/ArrayList/add(Ljava/lang/Object;)Z
		pop
		new List
		dup
		aload 9
		invokespecial List/<init>(Ljava/util/ArrayList;)V
		invokevirtual java/util/ArrayList/add(Ljava/lang/Object;)Z
		pop
		aload 8
		new java/util/ArrayList
		dup
		invokespecial java/util/ArrayList/<init>()V
		astore 9
		aload 9
		ldc ""
		invokevirtual java/util/ArrayList/add(Ljava/lang/Object;)Z
		pop
		aload 9
		ldc 0
		invokestatic java/lang/Integer/valueOf(I)Ljava/lang/Integer;
		invokevirtual java/util/ArrayList/add(Ljava/lang/Object;)Z
		pop
		new List
		dup
		aload 9
		invokespecial List/<init>(Ljava/util/ArrayList;)V
		invokevirtual java/util/ArrayList/add(Ljava/lang/Object;)Z
		pop
		aload 8
		new java/util/ArrayList
		dup
		invokespecial java/util/ArrayList/<init>()V
		astore 9
		aload 9
		ldc ""
		invokevirtual java/util/ArrayList/add(Ljava/lang/Object;)Z
		pop
		aload 9
		ldc 0
		invokestatic java/lang/Integer/valueOf(I)Ljava/lang/Integer;
		invokevirtual java/util/ArrayList/add(Ljava/lang/Object;)Z
		pop
		new List
		dup
		aload 9
		invokespecial List/<init>(Ljava/util/ArrayList;)V
		invokevirtual java/util/ArrayList/add(Ljava/lang/Object;)Z
		pop
		aload 8
		new java/util/ArrayList
		dup
		invokespecial java/util/ArrayList/<init>()V
		astore 9
		aload 9
		ldc ""
		invokevirtual java/util/ArrayList/add(Ljava/lang/Object;)Z
		pop
		aload 9
		ldc 0
		invokestatic java/lang/Integer/valueOf(I)Ljava/lang/Integer;
		invokevirtual java/util/ArrayList/add(Ljava/lang/Object;)Z
		pop
		new List
		dup
		aload 9
		invokespecial List/<init>(Ljava/util/ArrayList;)V
		invokevirtual java/util/ArrayList/add(Ljava/lang/Object;)Z
		pop
		aload 8
		new java/util/ArrayList
		dup
		invokespecial java/util/ArrayList/<init>()V
		astore 9
		aload 9
		ldc ""
		invokevirtual java/util/ArrayList/add(Ljava/lang/Object;)Z
		pop
		aload 9
		ldc 0
		invokestatic java/lang/Integer/valueOf(I)Ljava/lang/Integer;
		invokevirtual java/util/ArrayList/add(Ljava/lang/Object;)Z
		pop
		new List
		dup
		aload 9
		invokespecial List/<init>(Ljava/util/ArrayList;)V
		invokevirtual java/util/ArrayList/add(Ljava/lang/Object;)Z
		pop
		aload 8
		new java/util/ArrayList
		dup
		invokespecial java/util/ArrayList/<init>()V
		astore 9
		aload 9
		ldc ""
		invokevirtual java/util/ArrayList/add(Ljava/lang/Object;)Z
		pop
		aload 9
		ldc 0
		invokestatic java/lang/Integer/valueOf(I)Ljava/lang/Integer;
		invokevirtual java/util/ArrayList/add(Ljava/lang/Object;)Z
		pop
		new List
		dup
		aload 9
		invokespecial List/<init>(Ljava/util/ArrayList;)V
		invokevirtual java/util/ArrayList/add(Ljava/lang/Object;)Z
		pop
		aload 8
		new java/util/ArrayList
		dup
		invokespecial java/util/ArrayList/<init>()V
		astore 9
		aload 9
		ldc ""
		invokevirtual java/util/ArrayList/add(Ljava/lang/Object;)Z
		pop
		aload 9
		ldc 0
		invokestatic java/lang/Integer/valueOf(I)Ljava/lang/Integer;
		invokevirtual java/util/ArrayList/add(Ljava/lang/Object;)Z
		pop
		new List
		dup
		aload 9
		invokespecial List/<init>(Ljava/util/ArrayList;)V
		invokevirtual java/util/ArrayList/add(Ljava/lang/Object;)Z
		pop
		aload 8
		new java/util/ArrayList
		dup
		invokespecial java/util/ArrayList/<init>()V
		astore 9
		aload 9
		ldc ""
		invokevirtual java/util/ArrayList/add(Ljava/lang/Object;)Z
		pop
		aload 9
		ldc 0
		invokestatic java/lang/Integer/valueOf(I)Ljava/lang/Integer;
		invokevirtual java/util/ArrayList/add(Ljava/lang/Object;)Z
		pop
		new List
		dup
		aload 9
		invokespecial List/<init>(Ljava/util/ArrayList;)V
		invokevirtual java/util/ArrayList/add(Ljava/lang/Object;)Z
		pop
		aload 8
		new java/util/ArrayList
		dup
		invokespecial java/util/ArrayList/<init>()V
		astore 9
		aload 9
		ldc ""
		invokevirtual java/util/ArrayList/add(Ljava/lang/Object;)Z
		pop
		aload 9
		ldc 0
		invokestatic java/lang/Integer/valueOf(I)Ljava/lang/Integer;
		invokevirtual java/util/ArrayList/add(Ljava/lang/Object;)Z
		pop
		new List
		dup
		aload 9
		invokespecial List/<init>(Ljava/util/ArrayList;)V
		invokevirtual java/util/ArrayList/add(Ljava/lang/Object;)Z
		pop
		aload 8
		new java/util/ArrayList
		dup
		invokespecial java/util/ArrayList/<init>()V
		astore 9
		aload 9
		ldc ""
		invokevirtual java/util/ArrayList/add(Ljava/lang/Object;)Z
		pop
		aload 9
		ldc 0
		invokestatic java/lang/Integer/valueOf(I)Ljava/lang/Integer;
		invokevirtual java/util/ArrayList/add(Ljava/lang/Object;)Z
		pop
		new List
		dup
		aload 9
		invokespecial List/<init>(Ljava/util/ArrayList;)V
		invokevirtual java/util/ArrayList/add(Ljava/lang/Object;)Z
		pop
		aload 8
		new java/util/ArrayList
		dup
		invokespecial java/util/ArrayList/<init>()V
		astore 9
		aload 9
		ldc ""
		invokevirtual java/util/ArrayList/add(Ljava/lang/Object;)Z
		pop
		aload 9
		ldc 0
		invokestatic java/lang/Integer/valueOf(I)Ljava/lang/Integer;
		invokevirtual java/util/ArrayList/add(Ljava/lang/Object;)Z
		pop
		new List
		dup
		aload 9
		invokespecial List/<init>(Ljava/util/ArrayList;)V
		invokevirtual java/util/ArrayList/add(Ljava/lang/Object;)Z
		pop
		aload 8
		new java/util/ArrayList
		dup
		invokespecial java/util/ArrayList/<init>()V
		astore 9
		aload 9
		ldc ""
		invokevirtual java/util/ArrayList/add(Ljava/lang/Object;)Z
		pop
		aload 9
		ldc 0
		invokestatic java/lang/Integer/valueOf(I)Ljava/lang/Integer;
		invokevirtual java/util/ArrayList/add(Ljava/lang/Object;)Z
		pop
		new List
		dup
		aload 9
		invokespecial List/<init>(Ljava/util/ArrayList;)V
		invokevirtual java/util/ArrayList/add(Ljava/lang/Object;)Z
		pop
		aload 8
		new java/util/ArrayList
		dup
		invokespecial java/util/ArrayList/<init>()V
		astore 9
		aload 9
		ldc ""
		invokevirtual java/util/ArrayList/add(Ljava/lang/Object;)Z
		pop
		aload 9
		ldc 0
		invokestatic java/lang/Integer/valueOf(I)Ljava/lang/Integer;
		invokevirtual java/util/ArrayList/add(Ljava/lang/Object;)Z
		pop
		new List
		dup
		aload 9
		invokespecial List/<init>(Ljava/util/ArrayList;)V
		invokevirtual java/util/ArrayList/add(Ljava/lang/Object;)Z
		pop
		aload 8
		new java/util/ArrayList
		dup
		invokespecial java/util/ArrayList/<init>()V
		astore 9
		aload 9
		ldc ""
		invokevirtual java/util/ArrayList/add(Ljava/lang/Object;)Z
		pop
		aload 9
		ldc 0
		invokestatic java/lang/Integer/valueOf(I)Ljava/lang/Integer;
		invokevirtual java/util/ArrayList/add(Ljava/lang/Object;)Z
		pop
		new List
		dup
		aload 9
		invokespecial List/<init>(Ljava/util/ArrayList;)V
		invokevirtual java/util/ArrayList/add(Ljava/lang/Object;)Z
		pop
		aload 8
		new java/util/ArrayList
		dup
		invokespecial java/util/ArrayList/<init>()V
		astore 9
		aload 9
		ldc ""
		invokevirtual java/util/ArrayList/add(Ljava/lang/Object;)Z
		pop
		aload 9
		ldc 0
		invokestatic java/lang/Integer/valueOf(I)Ljava/lang/Integer;
		invokevirtual java/util/ArrayList/add(Ljava/lang/Object;)Z
		pop
		new List
		dup
		aload 9
		invokespecial List/<init>(Ljava/util/ArrayList;)V
		invokevirtual java/util/ArrayList/add(Ljava/lang/Object;)Z
		pop
		aload 8
		new java/util/ArrayList
		dup
		invokespecial java/util/ArrayList/<init>()V
		astore 9
		aload 9
		ldc ""
		invokevirtual java/util/ArrayList/add(Ljava/lang/Object;)Z
		pop
		aload 9
		ldc 0
		invokestatic java/lang/Integer/valueOf(I)Ljava/lang/Integer;
		invokevirtual java/util/ArrayList/add(Ljava/lang/Object;)Z
		pop
		new List
		dup
		aload 9
		invokespecial List/<init>(Ljava/util/ArrayList;)V
		invokevirtual java/util/ArrayList/add(Ljava/lang/Object;)Z
		pop
		aload 8
		new java/util/ArrayList
		dup
		invokespecial java/util/ArrayList/<init>()V
		astore 9
		aload 9
		ldc ""
		invokevirtual java/util/ArrayList/add(Ljava/lang/Object;)Z
		pop
		aload 9
		ldc 0
		invokestatic java/lang/Integer/valueOf(I)Ljava/lang/Integer;
		invokevirtual java/util/ArrayList/add(Ljava/lang/Object;)Z
		pop
		new List
		dup
		aload 9
		invokespecial List/<init>(Ljava/util/ArrayList;)V
		invokevirtual java/util/ArrayList/add(Ljava/lang/Object;)Z
		pop
		aload 8
		new java/util/ArrayList
		dup
		invokespecial java/util/ArrayList/<init>()V
		astore 9
		aload 9
		ldc ""
		invokevirtual java/util/ArrayList/add(Ljava/lang/Object;)Z
		pop
		aload 9
		ldc 0
		invokestatic java/lang/Integer/valueOf(I)Ljava/lang/Integer;
		invokevirtual java/util/ArrayList/add(Ljava/lang/Object;)Z
		pop
		new List
		dup
		aload 9
		invokespecial List/<init>(Ljava/util/ArrayList;)V
		invokevirtual java/util/ArrayList/add(Ljava/lang/Object;)Z
		pop
		new List
		dup
		aload 8
		invokespecial List/<init>(Ljava/util/ArrayList;)V
		astore 5
		ldc 0
		invokestatic java/lang/Integer/valueOf(I)Ljava/lang/Integer;
		astore 6
		new java/util/ArrayList
		dup
		invokespecial java/util/ArrayList/<init>()V
		astore 8
		aload 8
		ldc 0
		invokestatic java/lang/Integer/valueOf(I)Ljava/lang/Integer;
		invokevirtual java/util/ArrayList/add(Ljava/lang/Object;)Z
		pop
		aload 8
		ldc 0
		invokestatic java/lang/Integer/valueOf(I)Ljava/lang/Integer;
		invokevirtual java/util/ArrayList/add(Ljava/lang/Object;)Z
		pop
		new List
		dup
		aload 8
		invokespecial List/<init>(Ljava/util/ArrayList;)V
		astore 7
		ldc 0
		dup
		invokestatic java/lang/Integer/valueOf(I)Ljava/lang/Integer;
		astore 3
		pop
		ldc 0
		istore 8
	Label_0:
		iload 8
		aload 1
		getfield List/elements Ljava/util/ArrayList;
		invokevirtual java/util/ArrayList/size()I
		if_icmpge Label_1
		aload 1
		iload 8
		invokevirtual List/getElement(I)Ljava/lang/Object;
		checkcast java/lang/String
		astore 2
		iinc 8 1
		ldc 0
		dup
		invokestatic java/lang/Boolean/valueOf(Z)Ljava/lang/Boolean;
		astore 4
		pop
		ldc 0
		dup
		invokestatic java/lang/Integer/valueOf(I)Ljava/lang/Integer;
		astore 6
		pop
	Label_2:
		aload 6
		invokevirtual java/lang/Integer/intValue()I
		aload 3
		invokevirtual java/lang/Integer/intValue()I
		if_icmpge Label_5
		ldc 1
		goto Label_6
		Label_5:
		ldc 0
		Label_6:
		ifeq Label_3
		aload 5
		aload 6
		invokevirtual java/lang/Integer/intValue()I
		invokevirtual List/getElement(I)Ljava/lang/Object;
		checkcast List
		ldc 0
		invokevirtual List/getElement(I)Ljava/lang/Object;
		checkcast java/lang/String
		aload 2
		if_acmpne Label_9
		ldc 1
		goto Label_10
		Label_9:
		ldc 0
		Label_10:
		ifeq Label_7
		aload 5
		aload 6
		invokevirtual java/lang/Integer/intValue()I
		invokevirtual List/getElement(I)Ljava/lang/Object;
		checkcast List
		ldc 1
		aload 5
		aload 6
		invokevirtual java/lang/Integer/intValue()I
		invokevirtual List/getElement(I)Ljava/lang/Object;
		checkcast List
		ldc 1
		invokevirtual List/getElement(I)Ljava/lang/Object;
		checkcast java/lang/Integer
		invokevirtual java/lang/Integer/intValue()I
		ldc 1
		iadd
		dup_x2
		invokestatic java/lang/Integer/valueOf(I)Ljava/lang/Integer;
		invokevirtual List/setElement(ILjava/lang/Object;)V
		pop
		ldc 1
		dup
		invokestatic java/lang/Boolean/valueOf(Z)Ljava/lang/Boolean;
		astore 4
		pop
		goto Label_8
	Label_7:
	Label_8:
	Label_4:
		aload 6
		invokevirtual java/lang/Integer/intValue()I
		ldc 1
		iadd
		dup
		invokestatic java/lang/Integer/valueOf(I)Ljava/lang/Integer;
		astore 6
		pop
		goto Label_2
	Label_3:
		aload 4
		invokevirtual java/lang/Boolean/booleanValue()Z
		ifne Label_13
		ldc 1
		goto Label_14
		Label_13:
		ldc 0
		Label_14:
		ifeq Label_11
		aload 5
		aload 3
		invokevirtual java/lang/Integer/intValue()I
		invokevirtual List/getElement(I)Ljava/lang/Object;
		checkcast List
		ldc 0
		aload 2
		dup_x2
		invokevirtual List/setElement(ILjava/lang/Object;)V
		pop
		aload 5
		aload 3
		invokevirtual java/lang/Integer/intValue()I
		invokevirtual List/getElement(I)Ljava/lang/Object;
		checkcast List
		ldc 1
		ldc 1
		dup_x2
		invokestatic java/lang/Integer/valueOf(I)Ljava/lang/Integer;
		invokevirtual List/setElement(ILjava/lang/Object;)V
		pop
		aload 3
		invokevirtual java/lang/Integer/intValue()I
		ldc 1
		iadd
		dup
		invokestatic java/lang/Integer/valueOf(I)Ljava/lang/Integer;
		astore 3
		pop
		goto Label_12
	Label_11:
	Label_12:
		goto Label_0
	Label_1:
		new java/util/ArrayList
		dup
		invokespecial java/util/ArrayList/<init>()V
		astore 8
		aload 8
		aload 5
		invokevirtual java/util/ArrayList/add(Ljava/lang/Object;)Z
		pop
		aload 8
		aload 3
		invokevirtual java/lang/Integer/intValue()I
		invokestatic java/lang/Integer/valueOf(I)Ljava/lang/Integer;
		invokevirtual java/util/ArrayList/add(Ljava/lang/Object;)Z
		pop
		new List
		dup
		aload 8
		invokespecial List/<init>(Ljava/util/ArrayList;)V
		areturn
.end method
		 
.method public reduce(LList;LFptr;)Ljava/lang/Integer;
.limit stack 128
.limit locals 128
		ldc ""
		astore 3
		ldc 0
		invokestatic java/lang/Integer/valueOf(I)Ljava/lang/Integer;
		astore 4
		ldc 0
		invokestatic java/lang/Integer/valueOf(I)Ljava/lang/Integer;
		astore 5
		ldc 0
		dup
		invokestatic java/lang/Integer/valueOf(I)Ljava/lang/Integer;
		astore 4
		pop
		ldc 0
		dup
		invokestatic java/lang/Integer/valueOf(I)Ljava/lang/Integer;
		astore 5
		pop
	Label_15:
		aload 5
		invokevirtual java/lang/Integer/intValue()I
		aload 1
		ldc 1
		invokevirtual List/getElement(I)Ljava/lang/Object;
		checkcast java/lang/Integer
		invokevirtual java/lang/Integer/intValue()I
		if_icmpge Label_18
		ldc 1
		goto Label_19
		Label_18:
		ldc 0
		Label_19:
		ifeq Label_16
		new java/util/ArrayList
		dup
		invokespecial java/util/ArrayList/<init>()V
		astore 6
		aload 6
		aload 4
		invokevirtual java/lang/Integer/intValue()I
		invokestatic java/lang/Integer/valueOf(I)Ljava/lang/Integer;
		invokevirtual java/util/ArrayList/add(Ljava/lang/Object;)Z
		pop
		aload 6
		aload 1
		ldc 0
		invokevirtual List/getElement(I)Ljava/lang/Object;
		checkcast List
		aload 5
		invokevirtual java/lang/Integer/intValue()I
		invokevirtual List/getElement(I)Ljava/lang/Object;
		checkcast List
		ldc 1
		invokevirtual List/getElement(I)Ljava/lang/Object;
		checkcast java/lang/Integer
		invokevirtual java/lang/Integer/intValue()I
		invokestatic java/lang/Integer/valueOf(I)Ljava/lang/Integer;
		invokevirtual java/util/ArrayList/add(Ljava/lang/Object;)Z
		pop
		aload 2
		aload 6
		invokevirtual Fptr/invoke(Ljava/util/ArrayList;)Ljava/lang/Object;
		
		checkcast java/lang/Integer
		invokevirtual java/lang/Integer/intValue()I
		dup
		invokestatic java/lang/Integer/valueOf(I)Ljava/lang/Integer;
		astore 4
		pop
	Label_17:
		aload 5
		invokevirtual java/lang/Integer/intValue()I
		ldc 1
		iadd
		dup
		invokestatic java/lang/Integer/valueOf(I)Ljava/lang/Integer;
		astore 5
		pop
		goto Label_15
	Label_16:
		aload 4
		invokevirtual java/lang/Integer/intValue()I
		invokestatic java/lang/Integer/valueOf(I)Ljava/lang/Integer;
		areturn
.end method
		 
.method public add(Ljava/lang/Integer;Ljava/lang/Integer;)Ljava/lang/Integer;
.limit stack 128
.limit locals 128
		aload 1
		invokevirtual java/lang/Integer/intValue()I
		aload 2
		invokevirtual java/lang/Integer/intValue()I
		iadd
		invokestatic java/lang/Integer/valueOf(I)Ljava/lang/Integer;
		areturn
.end method
		 
.method public mul(Ljava/lang/Integer;Ljava/lang/Integer;)Ljava/lang/Integer;
.limit stack 128
.limit locals 128
		aload 1
		invokevirtual java/lang/Integer/intValue()I
		aload 2
		invokevirtual java/lang/Integer/intValue()I
		imul
		invokestatic java/lang/Integer/valueOf(I)Ljava/lang/Integer;
		areturn
.end method
		 
.method public wordProcess(LList;)V
.limit stack 128
.limit locals 128
		getstatic java/lang/System/out Ljava/io/PrintStream;
		ldc "the total number of names: "
		invokevirtual java/io/PrintStream/print(Ljava/lang/String;)V
		getstatic java/lang/System/out Ljava/io/PrintStream;
		new java/util/ArrayList
		dup
		invokespecial java/util/ArrayList/<init>()V
		astore 2
		aload 2
		new java/util/ArrayList
		dup
		invokespecial java/util/ArrayList/<init>()V
		astore 3
		aload 3
		aload 1
		invokevirtual java/util/ArrayList/add(Ljava/lang/Object;)Z
		pop
		new Fptr
		dup
		aload 0
		ldc "map"
		invokespecial Fptr/<init>(Ljava/lang/Object;Ljava/lang/String;)V
		aload 3
		invokevirtual Fptr/invoke(Ljava/util/ArrayList;)Ljava/lang/Object;
		
		checkcast List
		invokevirtual java/util/ArrayList/add(Ljava/lang/Object;)Z
		pop
		aload 2
		new Fptr
		dup
		aload 0
		ldc "add"
		invokespecial Fptr/<init>(Ljava/lang/Object;Ljava/lang/String;)V
		invokevirtual java/util/ArrayList/add(Ljava/lang/Object;)Z
		pop
		new Fptr
		dup
		aload 0
		ldc "reduce"
		invokespecial Fptr/<init>(Ljava/lang/Object;Ljava/lang/String;)V
		aload 2
		invokevirtual Fptr/invoke(Ljava/util/ArrayList;)Ljava/lang/Object;
		
		checkcast java/lang/Integer
		invokevirtual java/lang/Integer/intValue()I
		invokevirtual java/io/PrintStream/print(I)V
		return
.end method
		 
